{"995330": {"PerTested": 0.43200000000000005, "CR": 512, "Writing": 482, "NumTested": 63, "Math": 523, "M+CR+W": 1517, "M+CR": 1035}, "940316": {"PerTested": 0.47100000000000003, "CR": 393, "Writing": 382, "NumTested": 56, "Math": 426, "M+CR+W": 1201, "M+CR": 819}, "670670": {"PerTested": 0.51, "CR": 488, "Writing": 465, "NumTested": 657, "Math": 508, "M+CR+W": 1461, "M+CR": 996}, "970356": {"PerTested": 0.474, "CR": 499, "Writing": 473, "NumTested": 63, "Math": 508, "M+CR+W": 1480, "M+CR": 1007}, "890890": {"PerTested": 0.424, "CR": 466, "Writing": 422, "NumTested": 14, "Math": 494, "M+CR+W": 1382, "M+CR": 960}, "920588": {"PerTested": 0.688, "CR": 509, "Writing": 489, "NumTested": 289, "Math": 524, "M+CR+W": 1522, "M+CR": 1033}, "740366": {"PerTested": 0.63, "CR": 517, "Writing": 498, "NumTested": 225, "Math": 531, "M+CR+W": 1546, "M+CR": 1048}, "400400": {"PerTested": 0.515, "CR": 459, "Writing": 445, "NumTested": 87, "Math": 474, "M+CR+W": 1378, "M+CR": 933}, "140305": {"PerTested": 0.188, "CR": 428, "Writing": 415, "NumTested": 6, "Math": 452, "M+CR+W": 1295, "M+CR": 880}, "920595": {"PerTested": 0.7959999999999999, "CR": 513, "Writing": 500, "NumTested": 405, "Math": 537, "M+CR+W": 1550, "M+CR": 1050}, "360470": {"PerTested": 0.332, "CR": 449, "Writing": 428, "NumTested": 87, "Math": 479, "M+CR+W": 1356, "M+CR": 928}, "970970": {"PerTested": 0.47200000000000003, "CR": 510, "Writing": 482, "NumTested": 265, "Math": 527, "M+CR+W": 1519, "M+CR": 1037}, "290308": {"PerTested": 0.4, "CR": 488, "Writing": 478, "NumTested": 84, "Math": 519, "M+CR+W": 1485, "M+CR": 1007}, "910364": {"PerTested": 0.5489999999999999, "CR": 391, "Writing": 393, "NumTested": 101, "Math": 418, "M+CR+W": 1202, "M+CR": 809}, "610334": {"PerTested": 0.45299999999999996, "CR": 521, "Writing": 492, "NumTested": 63, "Math": 510, "M+CR+W": 1523, "M+CR": 1031}, "800800": {"PerTested": 0.506, "CR": 476, "Writing": 457, "NumTested": 625, "Math": 501, "M+CR+W": 1434, "M+CR": 977}, "840368": {"PerTested": 0.45899999999999996, "CR": 488, "Writing": 480, "NumTested": 107, "Math": 524, "M+CR+W": 1492, "M+CR": 1012}, "910370": {"PerTested": 0.535, "CR": 422, "Writing": 420, "NumTested": 107, "Math": 428, "M+CR+W": 1270, "M+CR": 850}, "132132": {"PerTested": 0.35700000000000004, "CR": 479, "Writing": 475, "NumTested": 81, "Math": 519, "M+CR+W": 1473, "M+CR": 998}, "420358": {"PerTested": 0.405, "CR": 394, "Writing": 383, "NumTested": 49, "Math": 396, "M+CR+W": 1173, "M+CR": 790}, "310310": {"PerTested": 0.47600000000000003, "CR": 439, "Writing": 422, "NumTested": 208, "Math": 449, "M+CR+W": 1310, "M+CR": 888}, "182316": {"PerTested": 0.7020000000000001, "CR": 477, "Writing": 459, "NumTested": 120, "Math": 510, "M+CR+W": 1446, "M+CR": 987}, "360494": {"PerTested": 0.649, "CR": 502, "Writing": 489, "NumTested": 189, "Math": 519, "M+CR+W": 1510, "M+CR": 1021}, "291336": {"PerTested": 0.46299999999999997, "CR": 433, "Writing": 423, "NumTested": 56, "Math": 443, "M+CR+W": 1299, "M+CR": 876}, "480307": {"PerTested": 0.41, "CR": 438, "Writing": 421, "NumTested": 16, "Math": 494, "M+CR+W": 1353, "M+CR": 932}, "260446": {"PerTested": 0.7020000000000001, "CR": 509, "Writing": 489, "NumTested": 214, "Math": 517, "M+CR+W": 1515, "M+CR": 1026}, "710710": {"PerTested": 0.531, "CR": 487, "Writing": 478, "NumTested": 233, "Math": 498, "M+CR+W": 1463, "M+CR": 985}, "660660": {"PerTested": 0.612, "CR": 401, "Writing": 401, "NumTested": 123, "Math": 411, "M+CR+W": 1213, "M+CR": 812}, "440378": {"PerTested": 0.43700000000000006, "CR": 499, "Writing": 494, "NumTested": 94, "Math": 524, "M+CR+W": 1517, "M+CR": 1023}, "140348": {"PerTested": 0.41700000000000004, "CR": 491, "Writing": 486, "NumTested": 88, "Math": 515, "M+CR+W": 1492, "M+CR": 1006}, "10303": {"PerTested": 0.16699999999999998, "CR": 486, "Writing": 474, "NumTested": 5, "Math": 516, "M+CR+W": 1476, "M+CR": 1002}, "950336": {"PerTested": 0.7170000000000001, "CR": 547, "Writing": 527, "NumTested": 215, "Math": 555, "M+CR+W": 1629, "M+CR": 1102}, "440390": {"PerTested": 0.5710000000000001, "CR": 519, "Writing": 509, "NumTested": 141, "Math": 563, "M+CR+W": 1591, "M+CR": 1082}, "320353": {"PerTested": 0.531, "CR": 564, "Writing": 544, "NumTested": 26, "Math": 524, "M+CR+W": 1632, "M+CR": 1088}, "310344": {"PerTested": 0.33299999999999996, "CR": 454, "Writing": 449, "NumTested": 53, "Math": 480, "M+CR+W": 1383, "M+CR": 934}, "181322": {"PerTested": 0.758, "CR": 508, "Writing": 499, "NumTested": 200, "Math": 534, "M+CR+W": 1541, "M+CR": 1042}, "620620": {"PerTested": 0.495, "CR": 423, "Writing": 409, "NumTested": 139, "Math": 444, "M+CR+W": 1276, "M+CR": 867}, "310352": {"PerTested": 0.602, "CR": 402, "Writing": 391, "NumTested": 68, "Math": 409, "M+CR+W": 1202, "M+CR": 811}, "130130": {"PerTested": 0.601, "CR": 505, "Writing": 489, "NumTested": 888, "Math": 529, "M+CR+W": 1523, "M+CR": 1034}, "10324": {"PerTested": 0.657, "CR": 489, "Writing": 467, "NumTested": 115, "Math": 529, "M+CR+W": 1485, "M+CR": 1018}, "650326": {"PerTested": 0.59, "CR": 497, "Writing": 480, "NumTested": 219, "Math": 510, "M+CR+W": 1487, "M+CR": 1007}, "650327": {"PerTested": 0.5579999999999999, "CR": 496, "Writing": 483, "NumTested": 168, "Math": 512, "M+CR+W": 1491, "M+CR": 1008}, "660324": {"PerTested": 0.8290000000000001, "CR": 395, "Writing": 405, "NumTested": 58, "Math": 403, "M+CR+W": 1203, "M+CR": 798}, "310364": {"PerTested": 0.6, "CR": 453, "Writing": 421, "NumTested": 33, "Math": 454, "M+CR+W": 1328, "M+CR": 907}, "180320": {"PerTested": 0.48100000000000004, "CR": 465, "Writing": 465, "NumTested": 75, "Math": 509, "M+CR+W": 1439, "M+CR": 974}, "600592": {"PerTested": 0.574, "CR": 462, "Writing": 445, "NumTested": 241, "Math": 467, "M+CR+W": 1374, "M+CR": 929}, "530530": {"PerTested": 0.545, "CR": 473, "Writing": 456, "NumTested": 270, "Math": 501, "M+CR+W": 1430, "M+CR": 974}, "350308": {"PerTested": 0.462, "CR": 487, "Writing": 464, "NumTested": 85, "Math": 498, "M+CR+W": 1449, "M+CR": 985}, "650342": {"PerTested": 0.8220000000000001, "CR": 522, "Writing": 509, "NumTested": 346, "Math": 551, "M+CR+W": 1582, "M+CR": 1073}, "780391": {"PerTested": 0.275, "CR": 377, "Writing": 372, "NumTested": 36, "Math": 421, "M+CR+W": 1170, "M+CR": 798}, "862312": {"PerTested": 0.544, "CR": 505, "Writing": 478, "NumTested": 68, "Math": 510, "M+CR+W": 1493, "M+CR": 1015}, "10348": {"PerTested": 0.546, "CR": 452, "Writing": 439, "NumTested": 89, "Math": 468, "M+CR+W": 1359, "M+CR": 920}, "800340": {"PerTested": 0.527, "CR": 483, "Writing": 464, "NumTested": 144, "Math": 507, "M+CR+W": 1454, "M+CR": 990}, "650352": {"PerTested": 0.604, "CR": 494, "Writing": 483, "NumTested": 215, "Math": 504, "M+CR+W": 1481, "M+CR": 998}, "350321": {"PerTested": 0.413, "CR": 465, "Writing": 467, "NumTested": 74, "Math": 477, "M+CR+W": 1409, "M+CR": 942}, "780402": {"PerTested": 0.4, "CR": 378, "Writing": 365, "NumTested": 42, "Math": 386, "M+CR+W": 1129, "M+CR": 764}, "180340": {"PerTested": 0.612, "CR": 501, "Writing": 486, "NumTested": 159, "Math": 540, "M+CR+W": 1527, "M+CR": 1041}, "990326": {"PerTested": 0.451, "CR": 476, "Writing": 472, "NumTested": 73, "Math": 494, "M+CR+W": 1442, "M+CR": 970}, "10360": {"PerTested": 0.58, "CR": 407, "Writing": 403, "NumTested": 87, "Math": 434, "M+CR+W": 1244, "M+CR": 841}, "180348": {"PerTested": 0.5589999999999999, "CR": 448, "Writing": 438, "NumTested": 85, "Math": 510, "M+CR+W": 1396, "M+CR": 958}, "340330": {"PerTested": 0.573, "CR": 393, "Writing": 382, "NumTested": 122, "Math": 397, "M+CR+W": 1172, "M+CR": 790}, "50302": {"PerTested": 0.503, "CR": 502, "Writing": 473, "NumTested": 93, "Math": 530, "M+CR+W": 1505, "M+CR": 1032}, "920703": {"PerTested": 0.129, "CR": 417, "Writing": 396, "NumTested": 9, "Math": 421, "M+CR+W": 1234, "M+CR": 838}, "350336": {"PerTested": 0.35, "CR": 473, "Writing": 457, "NumTested": 63, "Math": 483, "M+CR+W": 1413, "M+CR": 956}, "860352": {"PerTested": 0.401, "CR": 489, "Writing": 474, "NumTested": 63, "Math": 536, "M+CR+W": 1499, "M+CR": 1025}, "780420": {"PerTested": 0.446, "CR": 414, "Writing": 411, "NumTested": 135, "Math": 465, "M+CR+W": 1290, "M+CR": 879}, "740374": {"PerTested": 0.5479999999999999, "CR": 434, "Writing": 414, "NumTested": 74, "Math": 457, "M+CR+W": 1305, "M+CR": 891}, "780401": {"PerTested": 0.307, "CR": 459, "Writing": 428, "NumTested": 50, "Math": 461, "M+CR+W": 1348, "M+CR": 920}, "840840": {"PerTested": 0.475, "CR": 470, "Writing": 463, "NumTested": 307, "Math": 497, "M+CR+W": 1430, "M+CR": 967}, "190316": {"PerTested": 0.531, "CR": 479, "Writing": 473, "NumTested": 51, "Math": 511, "M+CR+W": 1463, "M+CR": 990}, "350350": {"PerTested": 0.409, "CR": 475, "Writing": 463, "NumTested": 222, "Math": 487, "M+CR+W": 1425, "M+CR": 962}, "690320": {"PerTested": 0.391, "CR": 482, "Writing": 459, "NumTested": 43, "Math": 509, "M+CR+W": 1450, "M+CR": 991}, "861861": {"PerTested": 0.5820000000000001, "CR": 514, "Writing": 487, "NumTested": 53, "Math": 532, "M+CR+W": 1533, "M+CR": 1046}, "10388": {"PerTested": 0.514, "CR": 485, "Writing": 480, "NumTested": 143, "Math": 507, "M+CR+W": 1472, "M+CR": 992}, "220310": {"PerTested": 0.705, "CR": 495, "Writing": 483, "NumTested": 55, "Math": 513, "M+CR+W": 1491, "M+CR": 1008}, "180376": {"PerTested": 0.612, "CR": 512, "Writing": 485, "NumTested": 161, "Math": 544, "M+CR+W": 1541, "M+CR": 1056}, "10396": {"PerTested": 0.764, "CR": 495, "Writing": 487, "NumTested": 204, "Math": 527, "M+CR+W": 1509, "M+CR": 1022}, "750750": {"PerTested": 0.556, "CR": 513, "Writing": 492, "NumTested": 85, "Math": 523, "M+CR+W": 1528, "M+CR": 1036}, "10400": {"PerTested": 0.701, "CR": 506, "Writing": 479, "NumTested": 178, "Math": 529, "M+CR+W": 1514, "M+CR": 1035}, "660336": {"PerTested": 0.5, "CR": 407, "Writing": 398, "NumTested": 65, "Math": 419, "M+CR+W": 1224, "M+CR": 826}, "260260": {"PerTested": 0.532, "CR": 469, "Writing": 453, "NumTested": 1708, "Math": 477, "M+CR+W": 1399, "M+CR": 946}, "70342": {"PerTested": 0.535, "CR": 468, "Writing": 453, "NumTested": 106, "Math": 497, "M+CR+W": 1418, "M+CR": 965}, "860336": {"PerTested": 0.313, "CR": 485, "Writing": 475, "NumTested": 68, "Math": 535, "M+CR+W": 1495, "M+CR": 1020}, "241316": {"PerTested": 0.542, "CR": 435, "Writing": 444, "NumTested": 77, "Math": 447, "M+CR+W": 1326, "M+CR": 882}, "390324": {"PerTested": 0.5, "CR": 465, "Writing": 444, "NumTested": 100, "Math": 482, "M+CR+W": 1391, "M+CR": 947}, "510324": {"PerTested": 0.5660000000000001, "CR": 500, "Writing": 480, "NumTested": 215, "Math": 517, "M+CR+W": 1497, "M+CR": 1017}, "170170": {"PerTested": 0.429, "CR": 459, "Writing": 441, "NumTested": 88, "Math": 476, "M+CR+W": 1376, "M+CR": 935}, "560320": {"PerTested": 0.586, "CR": 485, "Writing": 460, "NumTested": 119, "Math": 508, "M+CR+W": 1453, "M+CR": 993}, "460320": {"PerTested": 0.43700000000000006, "CR": 408, "Writing": 396, "NumTested": 97, "Math": 426, "M+CR+W": 1230, "M+CR": 834}, "560324": {"PerTested": 0.46399999999999997, "CR": 545, "Writing": 524, "NumTested": 13, "Math": 557, "M+CR+W": 1626, "M+CR": 1102}, "680310": {"PerTested": 0.823, "CR": 516, "Writing": 500, "NumTested": 186, "Math": 529, "M+CR+W": 1545, "M+CR": 1045}, "570570": {"PerTested": 0.466, "CR": 486, "Writing": 466, "NumTested": 61, "Math": 505, "M+CR+W": 1457, "M+CR": 991}, "132304": {"PerTested": 0.35700000000000004, "CR": 479, "Writing": 475, "NumTested": 81, "Math": 519, "M+CR+W": 1473, "M+CR": 998}, "861308": {"PerTested": 0.5820000000000001, "CR": 514, "Writing": 487, "NumTested": 53, "Math": 532, "M+CR+W": 1533, "M+CR": 1046}, "740388": {"PerTested": 0.7709999999999999, "CR": 464, "Writing": 451, "NumTested": 148, "Math": 485, "M+CR+W": 1400, "M+CR": 949}, "90330": {"PerTested": 0.565, "CR": 415, "Writing": 404, "NumTested": 87, "Math": 428, "M+CR+W": 1247, "M+CR": 843}, "900316": {"PerTested": 0.466, "CR": 463, "Writing": 453, "NumTested": 102, "Math": 496, "M+CR+W": 1412, "M+CR": 959}, "410490": {"PerTested": 0.772, "CR": 532, "Writing": 529, "NumTested": 402, "Math": 558, "M+CR+W": 1619, "M+CR": 1090}, "260318": {"PerTested": 0.619, "CR": 490, "Writing": 483, "NumTested": 245, "Math": 512, "M+CR+W": 1485, "M+CR": 1002}, "780325": {"PerTested": 0.342, "CR": 423, "Writing": 433, "NumTested": 52, "Math": 466, "M+CR+W": 1322, "M+CR": 889}, "480480": {"PerTested": 0.47700000000000004, "CR": 465, "Writing": 433, "NumTested": 21, "Math": 502, "M+CR+W": 1400, "M+CR": 967}, "260322": {"PerTested": 0.504, "CR": 424, "Writing": 408, "NumTested": 129, "Math": 422, "M+CR+W": 1254, "M+CR": 846}, "260325": {"PerTested": 0.429, "CR": 476, "Writing": 460, "NumTested": 124, "Math": 494, "M+CR+W": 1430, "M+CR": 970}, "681681": {"PerTested": 0.9309999999999999, "CR": 583, "Writing": 574, "NumTested": 737, "Math": 596, "M+CR+W": 1753, "M+CR": 1179}, "960380": {"PerTested": 0.435, "CR": 470, "Writing": 440, "NumTested": 93, "Math": 478, "M+CR+W": 1388, "M+CR": 948}, "600302": {"PerTested": 0.8490000000000001, "CR": 529, "Writing": 521, "NumTested": 264, "Math": 555, "M+CR+W": 1605, "M+CR": 1084}, "730352": {"PerTested": 0.535, "CR": 470, "Writing": 460, "NumTested": 199, "Math": 489, "M+CR+W": 1419, "M+CR": 959}, "390390": {"PerTested": 0.531, "CR": 467, "Writing": 448, "NumTested": 291, "Math": 476, "M+CR+W": 1391, "M+CR": 943}, "900344": {"PerTested": 0.644, "CR": 502, "Writing": 487, "NumTested": 172, "Math": 528, "M+CR+W": 1517, "M+CR": 1030}, "900348": {"PerTested": 0.674, "CR": 492, "Writing": 482, "NumTested": 126, "Math": 516, "M+CR+W": 1490, "M+CR": 1008}, "90368": {"PerTested": 0.503, "CR": 429, "Writing": 406, "NumTested": 74, "Math": 442, "M+CR+W": 1277, "M+CR": 871}, "260357": {"PerTested": 0.447, "CR": 477, "Writing": 452, "NumTested": 88, "Math": 477, "M+CR+W": 1406, "M+CR": 954}, "130310": {"PerTested": 0.652, "CR": 501, "Writing": 486, "NumTested": 236, "Math": 528, "M+CR+W": 1515, "M+CR": 1029}, "260359": {"PerTested": 0.49, "CR": 426, "Writing": 419, "NumTested": 121, "Math": 448, "M+CR+W": 1293, "M+CR": 874}, "900360": {"PerTested": 0.625, "CR": 502, "Writing": 493, "NumTested": 182, "Math": 512, "M+CR+W": 1507, "M+CR": 1014}, "290348": {"PerTested": 0.5820000000000001, "CR": 490, "Writing": 477, "NumTested": 185, "Math": 524, "M+CR+W": 1491, "M+CR": 1014}, "430346": {"PerTested": 0.489, "CR": 478, "Writing": 463, "NumTested": 130, "Math": 513, "M+CR+W": 1454, "M+CR": 991}, "300300": {"PerTested": 0.521, "CR": 508, "Writing": 495, "NumTested": 212, "Math": 526, "M+CR+W": 1529, "M+CR": 1034}, "960386": {"PerTested": 0.419, "CR": 492, "Writing": 468, "NumTested": 44, "Math": 506, "M+CR+W": 1466, "M+CR": 998}, "130324": {"PerTested": 0.536, "CR": 493, "Writing": 475, "NumTested": 113, "Math": 529, "M+CR+W": 1497, "M+CR": 1022}, "130326": {"PerTested": 0.637, "CR": 500, "Writing": 490, "NumTested": 205, "Math": 542, "M+CR+W": 1532, "M+CR": 1042}, "300312": {"PerTested": 0.521, "CR": 508, "Writing": 495, "NumTested": 212, "Math": 526, "M+CR+W": 1529, "M+CR": 1034}, "900377": {"PerTested": 0.9129999999999999, "CR": 522, "Writing": 514, "NumTested": 439, "Math": 549, "M+CR+W": 1585, "M+CR": 1071}, "700700": {"PerTested": 0.612, "CR": 448, "Writing": 433, "NumTested": 244, "Math": 450, "M+CR+W": 1331, "M+CR": 898}, "130333": {"PerTested": 0.5710000000000001, "CR": 398, "Writing": 365, "NumTested": 8, "Math": 364, "M+CR+W": 1127, "M+CR": 762}, "930352": {"PerTested": 0.5429999999999999, "CR": 413, "Writing": 406, "NumTested": 100, "Math": 423, "M+CR+W": 1242, "M+CR": 836}, "210210": {"PerTested": 0.52, "CR": 468, "Writing": 441, "NumTested": 66, "Math": 483, "M+CR+W": 1392, "M+CR": 951}, "430371": {"PerTested": 0.488, "CR": 465, "Writing": 437, "NumTested": 103, "Math": 457, "M+CR+W": 1359, "M+CR": 922}, "260388": {"PerTested": 0.774, "CR": 525, "Writing": 500, "NumTested": 48, "Math": 523, "M+CR+W": 1548, "M+CR": 1048}, "470312": {"PerTested": 0.619, "CR": 412, "Writing": 403, "NumTested": 205, "Math": 420, "M+CR+W": 1235, "M+CR": 832}, "600361": {"PerTested": 0.7659999999999999, "CR": 510, "Writing": 495, "NumTested": 400, "Math": 529, "M+CR+W": 1534, "M+CR": 1039}, "430378": {"PerTested": 0.387, "CR": 456, "Writing": 448, "NumTested": 86, "Math": 479, "M+CR+W": 1383, "M+CR": 935}, "770348": {"PerTested": 0.292, "CR": 459, "Writing": 453, "NumTested": 128, "Math": 491, "M+CR+W": 1403, "M+CR": 950}, "390706": {"PerTested": 0.146, "CR": 464, "Writing": 404, "NumTested": 13, "Math": 462, "M+CR+W": 1330, "M+CR": 926}, "430384": {"PerTested": 0.505, "CR": 477, "Writing": 449, "NumTested": 103, "Math": 484, "M+CR+W": 1410, "M+CR": 961}, "800361": {"PerTested": 0.375, "CR": 501, "Writing": 479, "NumTested": 66, "Math": 521, "M+CR+W": 1501, "M+CR": 1022}, "610610": {"PerTested": 0.45299999999999996, "CR": 521, "Writing": 492, "NumTested": 63, "Math": 510, "M+CR+W": 1523, "M+CR": 1031}, "120120": {"PerTested": 0.409, "CR": 492, "Writing": 472, "NumTested": 370, "Math": 521, "M+CR+W": 1485, "M+CR": 1013}, "260409": {"PerTested": 0.048, "CR": 0, "Writing": 0, "NumTested": 1, "Math": 0, "M+CR+W": 0, "M+CR": 0}, "260411": {"PerTested": 0.9209999999999999, "CR": 483, "Writing": 472, "NumTested": 70, "Math": 466, "M+CR+W": 1421, "M+CR": 949}, "600386": {"PerTested": 0.259, "CR": 414, "Writing": 403, "NumTested": 7, "Math": 429, "M+CR+W": 1246, "M+CR": 843}, "780342": {"PerTested": 0.46799999999999997, "CR": 445, "Writing": 438, "NumTested": 183, "Math": 465, "M+CR+W": 1348, "M+CR": 910}, "260424": {"PerTested": 0.42, "CR": 467, "Writing": 446, "NumTested": 142, "Math": 464, "M+CR+W": 1377, "M+CR": 931}, "410508": {"PerTested": 0.7240000000000001, "CR": 497, "Writing": 494, "NumTested": 249, "Math": 507, "M+CR+W": 1498, "M+CR": 1004}, "940940": {"PerTested": 0.439, "CR": 391, "Writing": 384, "NumTested": 61, "Math": 428, "M+CR+W": 1203, "M+CR": 819}, "260427": {"PerTested": 0.5379999999999999, "CR": 475, "Writing": 455, "NumTested": 198, "Math": 489, "M+CR+W": 1419, "M+CR": 964}, "170316": {"PerTested": 0.429, "CR": 459, "Writing": 441, "NumTested": 88, "Math": 476, "M+CR+W": 1376, "M+CR": 935}, "810324": {"PerTested": 0.348, "CR": 445, "Writing": 428, "NumTested": 73, "Math": 470, "M+CR+W": 1343, "M+CR": 915}, "600405": {"PerTested": 0.742, "CR": 456, "Writing": 445, "NumTested": 233, "Math": 457, "M+CR+W": 1358, "M+CR": 913}, "980342": {"PerTested": 0.502, "CR": 486, "Writing": 482, "NumTested": 118, "Math": 511, "M+CR+W": 1479, "M+CR": 997}, "920920": {"PerTested": 0.736, "CR": 518, "Writing": 506, "NumTested": 5611, "Math": 541, "M+CR+W": 1565, "M+CR": 1059}, "640346": {"PerTested": 0.45299999999999996, "CR": 453, "Writing": 443, "NumTested": 116, "Math": 486, "M+CR+W": 1382, "M+CR": 939}, "640347": {"PerTested": 0.267, "CR": 519, "Writing": 473, "NumTested": 8, "Math": 505, "M+CR+W": 1497, "M+CR": 1024}, "681308": {"PerTested": 0.9229999999999999, "CR": 578, "Writing": 576, "NumTested": 382, "Math": 600, "M+CR+W": 1754, "M+CR": 1178}, "430430": {"PerTested": 0.46299999999999997, "CR": 470, "Writing": 450, "NumTested": 422, "Math": 485, "M+CR+W": 1405, "M+CR": 955}, "600415": {"PerTested": 0.7090000000000001, "CR": 484, "Writing": 472, "NumTested": 360, "Math": 496, "M+CR+W": 1452, "M+CR": 980}, "360336": {"PerTested": 0.317, "CR": 477, "Writing": 459, "NumTested": 39, "Math": 487, "M+CR+W": 1423, "M+CR": 964}, "681314": {"PerTested": 0.9359999999999999, "CR": 590, "Writing": 572, "NumTested": 353, "Math": 594, "M+CR+W": 1756, "M+CR": 1184}, "810340": {"PerTested": 0.593, "CR": 449, "Writing": 447, "NumTested": 108, "Math": 468, "M+CR+W": 1364, "M+CR": 917}, "260455": {"PerTested": 0.46399999999999997, "CR": 419, "Writing": 403, "NumTested": 121, "Math": 416, "M+CR+W": 1238, "M+CR": 835}, "640361": {"PerTested": 0.527, "CR": 480, "Writing": 465, "NumTested": 128, "Math": 515, "M+CR+W": 1460, "M+CR": 995}, "600426": {"PerTested": 0.608, "CR": 460, "Writing": 438, "NumTested": 245, "Math": 460, "M+CR+W": 1358, "M+CR": 920}, "640364": {"PerTested": 0.318, "CR": 484, "Writing": 454, "NumTested": 91, "Math": 493, "M+CR+W": 1431, "M+CR": 977}, "920466": {"PerTested": 0.608, "CR": 455, "Writing": 436, "NumTested": 206, "Math": 463, "M+CR+W": 1354, "M+CR": 918}, "830830": {"PerTested": 0.5770000000000001, "CR": 451, "Writing": 441, "NumTested": 214, "Math": 481, "M+CR+W": 1373, "M+CR": 932}, "290365": {"PerTested": 0.405, "CR": 468, "Writing": 449, "NumTested": 34, "Math": 508, "M+CR+W": 1425, "M+CR": 976}, "980336": {"PerTested": 0.506, "CR": 481, "Writing": 462, "NumTested": 127, "Math": 501, "M+CR+W": 1444, "M+CR": 982}, "680680": {"PerTested": 0.775, "CR": 513, "Writing": 496, "NumTested": 347, "Math": 530, "M+CR+W": 1539, "M+CR": 1043}, "40306": {"PerTested": 0.466, "CR": 410, "Writing": 405, "NumTested": 95, "Math": 433, "M+CR+W": 1248, "M+CR": 843}, "340340": {"PerTested": 0.645, "CR": 499, "Writing": 488, "NumTested": 1997, "Math": 510, "M+CR+W": 1497, "M+CR": 1009}, "250340": {"PerTested": 0.363, "CR": 495, "Writing": 471, "NumTested": 107, "Math": 501, "M+CR+W": 1467, "M+CR": 996}, "680332": {"PerTested": 0.725, "CR": 508, "Writing": 492, "NumTested": 161, "Math": 531, "M+CR+W": 1531, "M+CR": 1039}, "740740": {"PerTested": 0.601, "CR": 485, "Writing": 469, "NumTested": 761, "Math": 505, "M+CR+W": 1459, "M+CR": 990}, "210312": {"PerTested": 0.52, "CR": 468, "Writing": 441, "NumTested": 66, "Math": 483, "M+CR+W": 1392, "M+CR": 951}, "250250": {"PerTested": 0.431, "CR": 481, "Writing": 461, "NumTested": 413, "Math": 503, "M+CR+W": 1445, "M+CR": 984}, "340364": {"PerTested": 0.6459999999999999, "CR": 527, "Writing": 513, "NumTested": 226, "Math": 533, "M+CR+W": 1573, "M+CR": 1060}, "810384": {"PerTested": 0.41700000000000004, "CR": 487, "Writing": 474, "NumTested": 95, "Math": 508, "M+CR+W": 1469, "M+CR": 995}, "600466": {"PerTested": 0.82, "CR": 570, "Writing": 557, "NumTested": 511, "Math": 584, "M+CR+W": 1711, "M+CR": 1154}, "380308": {"PerTested": 0.444, "CR": 483, "Writing": 462, "NumTested": 28, "Math": 483, "M+CR+W": 1428, "M+CR": 966}, "510357": {"PerTested": 0.318, "CR": 529, "Writing": 482, "NumTested": 14, "Math": 534, "M+CR+W": 1545, "M+CR": 1063}, "650650": {"PerTested": 0.634, "CR": 505, "Writing": 492, "NumTested": 948, "Math": 524, "M+CR+W": 1521, "M+CR": 1029}, "850332": {"PerTested": 0.37799999999999995, "CR": 484, "Writing": 465, "NumTested": 37, "Math": 503, "M+CR+W": 1452, "M+CR": 987}, "340382": {"PerTested": 0.584, "CR": 472, "Writing": 456, "NumTested": 201, "Math": 482, "M+CR+W": 1410, "M+CR": 954}, "600480": {"PerTested": 0.758, "CR": 515, "Writing": 503, "NumTested": 496, "Math": 534, "M+CR+W": 1552, "M+CR": 1049}, "880880": {"PerTested": 0.518, "CR": 515, "Writing": 495, "NumTested": 114, "Math": 529, "M+CR+W": 1539, "M+CR": 1044}, "600482": {"PerTested": 0.6559999999999999, "CR": 520, "Writing": 502, "NumTested": 80, "Math": 499, "M+CR+W": 1521, "M+CR": 1019}, "510376": {"PerTested": 0.386, "CR": 487, "Writing": 496, "NumTested": 22, "Math": 514, "M+CR+W": 1497, "M+CR": 1001}, "182700": {"PerTested": 0.7829999999999999, "CR": 451, "Writing": 433, "NumTested": 18, "Math": 490, "M+CR+W": 1374, "M+CR": 941}, "480316": {"PerTested": 1.0, "CR": 554, "Writing": 472, "NumTested": 5, "Math": 528, "M+CR+W": 1554, "M+CR": 1082}, "550320": {"PerTested": 0.6459999999999999, "CR": 474, "Writing": 456, "NumTested": 122, "Math": 505, "M+CR+W": 1435, "M+CR": 979}, "600498": {"PerTested": 0.46, "CR": 481, "Writing": 463, "NumTested": 23, "Math": 471, "M+CR+W": 1415, "M+CR": 952}, "240371": {"PerTested": 0.43799999999999994, "CR": 463, "Writing": 483, "NumTested": 56, "Math": 512, "M+CR+W": 1458, "M+CR": 975}, "422324": {"PerTested": 0.6, "CR": 379, "Writing": 373, "NumTested": 39, "Math": 409, "M+CR+W": 1161, "M+CR": 788}, "850358": {"PerTested": 0.485, "CR": 487, "Writing": 484, "NumTested": 115, "Math": 509, "M+CR+W": 1480, "M+CR": 996}, "80312": {"PerTested": 0.52, "CR": 408, "Writing": 403, "NumTested": 104, "Math": 424, "M+CR+W": 1235, "M+CR": 832}, "700319": {"PerTested": 0.551, "CR": 442, "Writing": 422, "NumTested": 108, "Math": 444, "M+CR+W": 1308, "M+CR": 886}, "550332": {"PerTested": 0.384, "CR": 477, "Writing": 456, "NumTested": 71, "Math": 505, "M+CR+W": 1438, "M+CR": 982}, "510399": {"PerTested": 0.514, "CR": 489, "Writing": 461, "NumTested": 132, "Math": 511, "M+CR+W": 1461, "M+CR": 1000}, "890304": {"PerTested": 0.424, "CR": 466, "Writing": 422, "NumTested": 14, "Math": 494, "M+CR+W": 1382, "M+CR": 960}, "160160": {"PerTested": 0.622, "CR": 517, "Writing": 494, "NumTested": 295, "Math": 527, "M+CR+W": 1538, "M+CR": 1044}, "510402": {"PerTested": 0.289, "CR": 492, "Writing": 480, "NumTested": 66, "Math": 525, "M+CR+W": 1497, "M+CR": 1017}, "421316": {"PerTested": 0.5429999999999999, "CR": 485, "Writing": 471, "NumTested": 95, "Math": 498, "M+CR+W": 1454, "M+CR": 983}, "900342": {"PerTested": 0.6579999999999999, "CR": 499, "Writing": 492, "NumTested": 181, "Math": 519, "M+CR+W": 1510, "M+CR": 1018}, "470470": {"PerTested": 0.605, "CR": 412, "Writing": 403, "NumTested": 205, "Math": 420, "M+CR+W": 1235, "M+CR": 832}, "761761": {"PerTested": 0.623, "CR": 492, "Writing": 479, "NumTested": 175, "Math": 517, "M+CR+W": 1488, "M+CR": 1009}, "550344": {"PerTested": 0.648, "CR": 478, "Writing": 476, "NumTested": 142, "Math": 510, "M+CR+W": 1464, "M+CR": 988}, "670344": {"PerTested": 0.49, "CR": 456, "Writing": 429, "NumTested": 76, "Math": 475, "M+CR+W": 1360, "M+CR": 931}, "840356": {"PerTested": 0.505, "CR": 471, "Writing": 467, "NumTested": 53, "Math": 513, "M+CR+W": 1451, "M+CR": 984}, "870870": {"PerTested": 0.45799999999999996, "CR": 496, "Writing": 482, "NumTested": 49, "Math": 504, "M+CR+W": 1482, "M+CR": 1000}, "600535": {"PerTested": 0.728, "CR": 502, "Writing": 486, "NumTested": 257, "Math": 525, "M+CR+W": 1513, "M+CR": 1027}, "761304": {"PerTested": 0.623, "CR": 492, "Writing": 479, "NumTested": 175, "Math": 517, "M+CR+W": 1488, "M+CR": 1009}, "291291": {"PerTested": 0.434, "CR": 433, "Writing": 423, "NumTested": 56, "Math": 443, "M+CR+W": 1299, "M+CR": 876}, "380380": {"PerTested": 0.444, "CR": 483, "Writing": 462, "NumTested": 28, "Math": 483, "M+CR+W": 1428, "M+CR": 966}, "340446": {"PerTested": 0.3, "CR": 540, "Writing": 532, "NumTested": 12, "Math": 526, "M+CR+W": 1598, "M+CR": 1066}, "600376": {"PerTested": 0.41, "CR": 453, "Writing": 439, "NumTested": 66, "Math": 457, "M+CR+W": 1349, "M+CR": 910}, "550368": {"PerTested": 0.483, "CR": 468, "Writing": 446, "NumTested": 97, "Math": 494, "M+CR+W": 1408, "M+CR": 962}, "292324": {"PerTested": 0.5579999999999999, "CR": 443, "Writing": 425, "NumTested": 72, "Math": 461, "M+CR+W": 1329, "M+CR": 904}, "920316": {"PerTested": 0.845, "CR": 543, "Writing": 531, "NumTested": 474, "Math": 573, "M+CR+W": 1647, "M+CR": 1116}, "340454": {"PerTested": 0.782, "CR": 539, "Writing": 527, "NumTested": 290, "Math": 554, "M+CR+W": 1620, "M+CR": 1093}, "240380": {"PerTested": 0.42, "CR": 427, "Writing": 395, "NumTested": 47, "Math": 426, "M+CR+W": 1248, "M+CR": 853}, "640350": {"PerTested": 0.51, "CR": 474, "Writing": 457, "NumTested": 132, "Math": 485, "M+CR+W": 1416, "M+CR": 959}, "340460": {"PerTested": 0.527, "CR": 452, "Writing": 441, "NumTested": 139, "Math": 453, "M+CR+W": 1346, "M+CR": 905}, "220220": {"PerTested": 0.705, "CR": 495, "Writing": 483, "NumTested": 55, "Math": 513, "M+CR+W": 1491, "M+CR": 1008}, "710342": {"PerTested": 0.72, "CR": 516, "Writing": 503, "NumTested": 116, "Math": 519, "M+CR+W": 1538, "M+CR": 1035}, "360360": {"PerTested": 0.387, "CR": 483, "Writing": 469, "NumTested": 55, "Math": 522, "M+CR+W": 1474, "M+CR": 1005}, "290290": {"PerTested": 0.498, "CR": 495, "Writing": 480, "NumTested": 600, "Math": 518, "M+CR+W": 1493, "M+CR": 1013}, "250356": {"PerTested": 0.564, "CR": 477, "Writing": 463, "NumTested": 238, "Math": 504, "M+CR+W": 1444, "M+CR": 981}, "920318": {"PerTested": 0.768, "CR": 518, "Writing": 505, "NumTested": 295, "Math": 553, "M+CR+W": 1576, "M+CR": 1071}, "120310": {"PerTested": 0.667, "CR": 496, "Writing": 505, "NumTested": 20, "Math": 501, "M+CR+W": 1502, "M+CR": 997}, "110323": {"PerTested": 0.18899999999999997, "CR": 536, "Writing": 514, "NumTested": 7, "Math": 461, "M+CR+W": 1511, "M+CR": 997}, "180308": {"PerTested": 0.575, "CR": 477, "Writing": 460, "NumTested": 122, "Math": 504, "M+CR+W": 1441, "M+CR": 981}, "420346": {"PerTested": 0.44799999999999995, "CR": 398, "Writing": 399, "NumTested": 81, "Math": 416, "M+CR+W": 1213, "M+CR": 814}, "800376": {"PerTested": 0.607, "CR": 459, "Writing": 439, "NumTested": 71, "Math": 481, "M+CR+W": 1379, "M+CR": 940}, "120318": {"PerTested": 0.493, "CR": 503, "Writing": 484, "NumTested": 178, "Math": 528, "M+CR+W": 1515, "M+CR": 1031}, "600576": {"PerTested": 0.488, "CR": 397, "Writing": 392, "NumTested": 157, "Math": 416, "M+CR+W": 1205, "M+CR": 813}, "120314": {"PerTested": 0.415, "CR": 480, "Writing": 453, "NumTested": 158, "Math": 516, "M+CR+W": 1449, "M+CR": 996}, "690690": {"PerTested": 0.391, "CR": 482, "Writing": 459, "NumTested": 43, "Math": 509, "M+CR+W": 1450, "M+CR": 991}, "600579": {"PerTested": 0.384, "CR": 436, "Writing": 428, "NumTested": 104, "Math": 457, "M+CR+W": 1321, "M+CR": 893}, "250372": {"PerTested": 0.28300000000000003, "CR": 477, "Writing": 440, "NumTested": 68, "Math": 503, "M+CR+W": 1420, "M+CR": 980}, "340486": {"PerTested": 0.551, "CR": 430, "Writing": 413, "NumTested": 158, "Math": 441, "M+CR+W": 1284, "M+CR": 871}, "111111": {"PerTested": 0.8190000000000001, "CR": 539, "Writing": 505, "NumTested": 195, "Math": 527, "M+CR+W": 1571, "M+CR": 1066}, "200200": {"PerTested": 0.518, "CR": 484, "Writing": 466, "NumTested": 114, "Math": 504, "M+CR+W": 1454, "M+CR": 988}, "290315": {"PerTested": 1.0, "CR": 542, "Writing": 493, "NumTested": 9, "Math": 538, "M+CR+W": 1573, "M+CR": 1080}, "900336": {"PerTested": 0.569, "CR": 433, "Writing": 412, "NumTested": 87, "Math": 465, "M+CR+W": 1310, "M+CR": 898}, "340495": {"PerTested": 0.773, "CR": 539, "Writing": 528, "NumTested": 197, "Math": 542, "M+CR+W": 1609, "M+CR": 1081}, "340496": {"PerTested": 0.64, "CR": 535, "Writing": 529, "NumTested": 185, "Math": 544, "M+CR+W": 1608, "M+CR": 1079}, "330328": {"PerTested": 0.239, "CR": 444, "Writing": 426, "NumTested": 16, "Math": 474, "M+CR+W": 1344, "M+CR": 918}, "290324": {"PerTested": 0.568, "CR": 489, "Writing": 480, "NumTested": 96, "Math": 503, "M+CR+W": 1472, "M+CR": 992}, "422422": {"PerTested": 0.6, "CR": 379, "Writing": 373, "NumTested": 39, "Math": 409, "M+CR+W": 1161, "M+CR": 788}, "600600": {"PerTested": 0.684, "CR": 496, "Writing": 483, "NumTested": 4656, "Math": 510, "M+CR+W": 1489, "M+CR": 1006}, "100100": {"PerTested": 0.423, "CR": 496, "Writing": 481, "NumTested": 284, "Math": 507, "M+CR+W": 1484, "M+CR": 1003}, "760348": {"PerTested": 0.515, "CR": 468, "Writing": 454, "NumTested": 105, "Math": 502, "M+CR+W": 1424, "M+CR": 970}, "110110": {"PerTested": 0.551, "CR": 522, "Writing": 505, "NumTested": 804, "Math": 542, "M+CR+W": 1569, "M+CR": 1064}, "290336": {"PerTested": 0.609, "CR": 515, "Writing": 503, "NumTested": 131, "Math": 527, "M+CR+W": 1545, "M+CR": 1042}, "560560": {"PerTested": 0.57, "CR": 490, "Writing": 465, "NumTested": 135, "Math": 512, "M+CR+W": 1467, "M+CR": 1002}, "790790": {"PerTested": 0.562, "CR": 480, "Writing": 461, "NumTested": 429, "Math": 492, "M+CR+W": 1433, "M+CR": 972}, "760358": {"PerTested": 0.38299999999999995, "CR": 491, "Writing": 471, "NumTested": 98, "Math": 502, "M+CR+W": 1464, "M+CR": 993}, "390700": {"PerTested": 0.644, "CR": 470, "Writing": 465, "NumTested": 47, "Math": 487, "M+CR+W": 1422, "M+CR": 957}, "421421": {"PerTested": 0.5429999999999999, "CR": 485, "Writing": 471, "NumTested": 95, "Math": 498, "M+CR+W": 1454, "M+CR": 983}, "510510": {"PerTested": 0.456, "CR": 498, "Writing": 479, "NumTested": 697, "Math": 521, "M+CR+W": 1498, "M+CR": 1019}, "390704": {"PerTested": 0.47700000000000004, "CR": 457, "Writing": 445, "NumTested": 41, "Math": 460, "M+CR+W": 1362, "M+CR": 917}, "390705": {"PerTested": 0.299, "CR": 461, "Writing": 442, "NumTested": 29, "Math": 458, "M+CR+W": 1361, "M+CR": 919}, "120370": {"PerTested": 0.156, "CR": 496, "Writing": 479, "NumTested": 14, "Math": 501, "M+CR+W": 1476, "M+CR": 997}, "160313": {"PerTested": 0.528, "CR": 521, "Writing": 496, "NumTested": 66, "Math": 503, "M+CR+W": 1520, "M+CR": 1024}, "160314": {"PerTested": 0.7829999999999999, "CR": 528, "Writing": 503, "NumTested": 112, "Math": 535, "M+CR+W": 1566, "M+CR": 1063}, "630332": {"PerTested": 0.34700000000000003, "CR": 490, "Writing": 482, "NumTested": 52, "Math": 518, "M+CR+W": 1490, "M+CR": 1008}, "130314": {"PerTested": 0.61, "CR": 527, "Writing": 494, "NumTested": 128, "Math": 518, "M+CR+W": 1539, "M+CR": 1045}, "910910": {"PerTested": 0.494, "CR": 407, "Writing": 407, "NumTested": 208, "Math": 423, "M+CR+W": 1237, "M+CR": 830}, "630336": {"PerTested": 0.601, "CR": 512, "Writing": 498, "NumTested": 256, "Math": 550, "M+CR+W": 1560, "M+CR": 1062}, "420420": {"PerTested": 0.434, "CR": 397, "Writing": 394, "NumTested": 131, "Math": 408, "M+CR+W": 1199, "M+CR": 805}, "990322": {"PerTested": 0.449, "CR": 489, "Writing": 468, "NumTested": 96, "Math": 507, "M+CR+W": 1464, "M+CR": 996}, "130316": {"PerTested": 0.555, "CR": 512, "Writing": 501, "NumTested": 198, "Math": 531, "M+CR+W": 1544, "M+CR": 1043}, "340556": {"PerTested": 0.77, "CR": 527, "Writing": 521, "NumTested": 339, "Math": 560, "M+CR+W": 1608, "M+CR": 1087}, "140386": {"PerTested": 0.43799999999999994, "CR": 503, "Writing": 489, "NumTested": 147, "Math": 530, "M+CR+W": 1522, "M+CR": 1033}, "970320": {"PerTested": 0.418, "CR": 519, "Writing": 507, "NumTested": 41, "Math": 529, "M+CR+W": 1555, "M+CR": 1048}, "290388": {"PerTested": 0.40700000000000003, "CR": 493, "Writing": 462, "NumTested": 61, "Math": 501, "M+CR+W": 1456, "M+CR": 994}, "330326": {"PerTested": 0.385, "CR": 408, "Writing": 394, "NumTested": 5, "Math": 400, "M+CR+W": 1202, "M+CR": 808}, "160344": {"PerTested": 0.568, "CR": 504, "Writing": 484, "NumTested": 117, "Math": 533, "M+CR+W": 1521, "M+CR": 1037}, "241241": {"PerTested": 0.52, "CR": 435, "Writing": 444, "NumTested": 77, "Math": 447, "M+CR+W": 1326, "M+CR": 882}, "330330": {"PerTested": 0.425, "CR": 434, "Writing": 429, "NumTested": 176, "Math": 452, "M+CR+W": 1315, "M+CR": 886}, "500316": {"PerTested": 0.522, "CR": 447, "Writing": 400, "NumTested": 12, "Math": 428, "M+CR+W": 1275, "M+CR": 875}, "30304": {"PerTested": 0.43700000000000006, "CR": 480, "Writing": 464, "NumTested": 52, "Math": 519, "M+CR+W": 1463, "M+CR": 999}, "110352": {"PerTested": 0.522, "CR": 501, "Writing": 481, "NumTested": 129, "Math": 510, "M+CR+W": 1492, "M+CR": 1011}, "140390": {"PerTested": 0.413, "CR": 469, "Writing": 451, "NumTested": 74, "Math": 509, "M+CR+W": 1429, "M+CR": 978}, "600508": {"PerTested": 0.9259999999999999, "CR": 550, "Writing": 549, "NumTested": 398, "Math": 577, "M+CR+W": 1676, "M+CR": 1127}, "730730": {"PerTested": 0.535, "CR": 470, "Writing": 460, "NumTested": 199, "Math": 489, "M+CR+W": 1419, "M+CR": 959}, "330350": {"PerTested": 0.40299999999999997, "CR": 441, "Writing": 431, "NumTested": 71, "Math": 461, "M+CR+W": 1333, "M+CR": 902}, "240240": {"PerTested": 0.46799999999999997, "CR": 438, "Writing": 431, "NumTested": 163, "Math": 459, "M+CR+W": 1328, "M+CR": 897}, "850352": {"PerTested": 0.41700000000000004, "CR": 488, "Writing": 472, "NumTested": 63, "Math": 515, "M+CR+W": 1475, "M+CR": 1003}, "200308": {"PerTested": 0.623, "CR": 445, "Writing": 439, "NumTested": 33, "Math": 477, "M+CR+W": 1361, "M+CR": 922}, "600693": {"PerTested": 0.609, "CR": 486, "Writing": 457, "NumTested": 42, "Math": 469, "M+CR+W": 1412, "M+CR": 955}, "330358": {"PerTested": 0.532, "CR": 429, "Writing": 429, "NumTested": 84, "Math": 443, "M+CR+W": 1301, "M+CR": 872}, "600695": {"PerTested": 0.6, "CR": 478, "Writing": 448, "NumTested": 39, "Math": 457, "M+CR+W": 1383, "M+CR": 935}, "600696": {"PerTested": 0.7559999999999999, "CR": 443, "Writing": 413, "NumTested": 59, "Math": 431, "M+CR+W": 1287, "M+CR": 874}, "600697": {"PerTested": 0.75, "CR": 433, "Writing": 429, "NumTested": 54, "Math": 449, "M+CR+W": 1311, "M+CR": 882}, "200314": {"PerTested": 0.359, "CR": 510, "Writing": 489, "NumTested": 14, "Math": 540, "M+CR+W": 1539, "M+CR": 1050}, "670333": {"PerTested": 0.505, "CR": 480, "Writing": 467, "NumTested": 94, "Math": 497, "M+CR+W": 1444, "M+CR": 977}, "640640": {"PerTested": 0.442, "CR": 473, "Writing": 455, "NumTested": 475, "Math": 495, "M+CR+W": 1423, "M+CR": 968}, "960960": {"PerTested": 0.493, "CR": 484, "Writing": 459, "NumTested": 562, "Math": 495, "M+CR+W": 1438, "M+CR": 979}, "670340": {"PerTested": 0.406, "CR": 502, "Writing": 467, "NumTested": 71, "Math": 507, "M+CR+W": 1476, "M+CR": 1009}, "150150": {"PerTested": 0.588, "CR": 476, "Writing": 458, "NumTested": 77, "Math": 490, "M+CR+W": 1424, "M+CR": 966}, "200328": {"PerTested": 0.638, "CR": 498, "Writing": 474, "NumTested": 67, "Math": 509, "M+CR+W": 1481, "M+CR": 1007}, "800396": {"PerTested": 0.736, "CR": 463, "Writing": 444, "NumTested": 128, "Math": 482, "M+CR+W": 1389, "M+CR": 945}, "862862": {"PerTested": 0.544, "CR": 505, "Writing": 478, "NumTested": 68, "Math": 510, "M+CR+W": 1493, "M+CR": 1015}, "670352": {"PerTested": 0.462, "CR": 510, "Writing": 480, "NumTested": 78, "Math": 528, "M+CR+W": 1518, "M+CR": 1038}, "970388": {"PerTested": 0.474, "CR": 526, "Writing": 490, "NumTested": 55, "Math": 548, "M+CR+W": 1564, "M+CR": 1074}, "840302": {"PerTested": 0.528, "CR": 456, "Writing": 448, "NumTested": 76, "Math": 466, "M+CR+W": 1370, "M+CR": 922}, "550550": {"PerTested": 0.544, "CR": 474, "Writing": 460, "NumTested": 432, "Math": 504, "M+CR+W": 1438, "M+CR": 978}, "920552": {"PerTested": 0.723, "CR": 513, "Writing": 496, "NumTested": 259, "Math": 535, "M+CR+W": 1544, "M+CR": 1048}, "800408": {"PerTested": 0.461, "CR": 474, "Writing": 453, "NumTested": 117, "Math": 500, "M+CR+W": 1427, "M+CR": 974}, "292292": {"PerTested": 0.5579999999999999, "CR": 443, "Writing": 425, "NumTested": 72, "Math": 461, "M+CR+W": 1329, "M+CR": 904}, "800400": {"PerTested": 0.41700000000000004, "CR": 487, "Writing": 464, "NumTested": 96, "Math": 521, "M+CR+W": 1472, "M+CR": 1008}, "540315": {"PerTested": 0.493, "CR": 443, "Writing": 429, "NumTested": 103, "Math": 476, "M+CR+W": 1348, "M+CR": 919}, "670364": {"PerTested": 0.493, "CR": 500, "Writing": 482, "NumTested": 111, "Math": 539, "M+CR+W": 1521, "M+CR": 1039}, "670320": {"PerTested": 0.56, "CR": 511, "Writing": 494, "NumTested": 70, "Math": 520, "M+CR+W": 1525, "M+CR": 1031}, "540324": {"PerTested": 0.35600000000000004, "CR": 460, "Writing": 449, "NumTested": 73, "Math": 488, "M+CR+W": 1397, "M+CR": 948}, "510406": {"PerTested": 0.483, "CR": 508, "Writing": 487, "NumTested": 200, "Math": 525, "M+CR+W": 1520, "M+CR": 1033}, "950950": {"PerTested": 0.7170000000000001, "CR": 547, "Writing": 527, "NumTested": 215, "Math": 555, "M+CR+W": 1629, "M+CR": 1102}, "720316": {"PerTested": 0.51, "CR": 456, "Writing": 423, "NumTested": 53, "Math": 480, "M+CR+W": 1359, "M+CR": 936}, "920348": {"PerTested": 0.85, "CR": 530, "Writing": 524, "NumTested": 373, "Math": 548, "M+CR+W": 1602, "M+CR": 1078}, "460460": {"PerTested": 0.43700000000000006, "CR": 408, "Writing": 396, "NumTested": 97, "Math": 426, "M+CR+W": 1230, "M+CR": 834}, "930930": {"PerTested": 0.5429999999999999, "CR": 413, "Writing": 406, "NumTested": 100, "Math": 423, "M+CR+W": 1242, "M+CR": 836}, "540336": {"PerTested": 0.358, "CR": 509, "Writing": 498, "NumTested": 58, "Math": 533, "M+CR+W": 1540, "M+CR": 1042}, "710321": {"PerTested": 0.452, "CR": 475, "Writing": 465, "NumTested": 57, "Math": 480, "M+CR+W": 1420, "M+CR": 955}, "880308": {"PerTested": 0.604, "CR": 526, "Writing": 502, "NumTested": 84, "Math": 541, "M+CR+W": 1569, "M+CR": 1067}, "710326": {"PerTested": 0.395, "CR": 441, "Writing": 442, "NumTested": 60, "Math": 474, "M+CR+W": 1357, "M+CR": 915}, "500340": {"PerTested": 0.59, "CR": 492, "Writing": 468, "NumTested": 108, "Math": 504, "M+CR+W": 1464, "M+CR": 996}, "70330": {"PerTested": 0.47700000000000004, "CR": 505, "Writing": 478, "NumTested": 41, "Math": 529, "M+CR+W": 1512, "M+CR": 1034}, "860860": {"PerTested": 0.386, "CR": 491, "Writing": 477, "NumTested": 202, "Math": 532, "M+CR+W": 1500, "M+CR": 1023}, "370370": {"PerTested": 0.4, "CR": 465, "Writing": 455, "NumTested": 54, "Math": 495, "M+CR+W": 1415, "M+CR": 960}, "70339": {"PerTested": 0.344, "CR": 461, "Writing": 464, "NumTested": 32, "Math": 505, "M+CR+W": 1430, "M+CR": 966}, "111302": {"PerTested": 0.8190000000000001, "CR": 539, "Writing": 505, "NumTested": 195, "Math": 527, "M+CR+W": 1571, "M+CR": 1066}, "880328": {"PerTested": 0.484, "CR": 483, "Writing": 477, "NumTested": 30, "Math": 496, "M+CR+W": 1456, "M+CR": 979}, "240334": {"PerTested": 0.556, "CR": 423, "Writing": 410, "NumTested": 60, "Math": 435, "M+CR+W": 1268, "M+CR": 858}, "410319": {"PerTested": 0.5870000000000001, "CR": 433, "Writing": 422, "NumTested": 125, "Math": 436, "M+CR+W": 1291, "M+CR": 869}, "580304": {"PerTested": 0.47200000000000003, "CR": 500, "Writing": 494, "NumTested": 17, "Math": 586, "M+CR+W": 1580, "M+CR": 1086}, "310392": {"PerTested": 0.491, "CR": 461, "Writing": 436, "NumTested": 54, "Math": 466, "M+CR+W": 1363, "M+CR": 927}, "770770": {"PerTested": 0.281, "CR": 459, "Writing": 453, "NumTested": 128, "Math": 491, "M+CR+W": 1403, "M+CR": 950}, "230350": {"PerTested": 0.49, "CR": 489, "Writing": 471, "NumTested": 118, "Math": 523, "M+CR+W": 1483, "M+CR": 1012}, "410326": {"PerTested": 0.414, "CR": 375, "Writing": 365, "NumTested": 12, "Math": 399, "M+CR+W": 1139, "M+CR": 774}, "280280": {"PerTested": 0.784, "CR": 503, "Writing": 485, "NumTested": 265, "Math": 521, "M+CR+W": 1509, "M+CR": 1024}, "340700": {"PerTested": 0.529, "CR": 411, "Writing": 386, "NumTested": 18, "Math": 414, "M+CR+W": 1211, "M+CR": 825}, "340701": {"PerTested": 0.425, "CR": 408, "Writing": 382, "NumTested": 17, "Math": 396, "M+CR+W": 1186, "M+CR": 804}, "340702": {"PerTested": 0.647, "CR": 387, "Writing": 375, "NumTested": 22, "Math": 407, "M+CR+W": 1169, "M+CR": 794}, "110304": {"PerTested": 0.5760000000000001, "CR": 544, "Writing": 516, "NumTested": 155, "Math": 559, "M+CR+W": 1619, "M+CR": 1103}, "580328": {"PerTested": 0.47100000000000003, "CR": 508, "Writing": 463, "NumTested": 16, "Math": 535, "M+CR+W": 1506, "M+CR": 1043}, "820348": {"PerTested": 0.48200000000000004, "CR": 429, "Writing": 420, "NumTested": 53, "Math": 472, "M+CR+W": 1321, "M+CR": 901}, "790378": {"PerTested": 0.601, "CR": 487, "Writing": 470, "NumTested": 122, "Math": 513, "M+CR+W": 1470, "M+CR": 1000}, "190190": {"PerTested": 0.579, "CR": 492, "Writing": 481, "NumTested": 281, "Math": 506, "M+CR+W": 1479, "M+CR": 998}, "820349": {"PerTested": 0.449, "CR": 431, "Writing": 408, "NumTested": 48, "Math": 439, "M+CR+W": 1278, "M+CR": 870}, "280304": {"PerTested": 0.794, "CR": 509, "Writing": 500, "NumTested": 27, "Math": 529, "M+CR+W": 1538, "M+CR": 1038}, "920700": {"PerTested": 0.466, "CR": 460, "Writing": 440, "NumTested": 41, "Math": 472, "M+CR+W": 1372, "M+CR": 932}, "410355": {"PerTested": 0.537, "CR": 417, "Writing": 418, "NumTested": 145, "Math": 438, "M+CR+W": 1273, "M+CR": 855}, "820352": {"PerTested": 0.509, "CR": 456, "Writing": 453, "NumTested": 59, "Math": 495, "M+CR+W": 1404, "M+CR": 951}, "920702": {"PerTested": 0.12, "CR": 425, "Writing": 428, "NumTested": 10, "Math": 457, "M+CR+W": 1310, "M+CR": 882}, "410358": {"PerTested": 0.5489999999999999, "CR": 460, "Writing": 442, "NumTested": 95, "Math": 473, "M+CR+W": 1375, "M+CR": 933}, "580344": {"PerTested": 0.419, "CR": 414, "Writing": 391, "NumTested": 36, "Math": 451, "M+CR+W": 1256, "M+CR": 865}, "280316": {"PerTested": 0.7290000000000001, "CR": 497, "Writing": 470, "NumTested": 70, "Math": 510, "M+CR+W": 1477, "M+CR": 1007}, "790314": {"PerTested": 0.516, "CR": 500, "Writing": 471, "NumTested": 94, "Math": 500, "M+CR+W": 1471, "M+CR": 1000}, "590590": {"PerTested": 0.40399999999999997, "CR": 492, "Writing": 470, "NumTested": 157, "Math": 506, "M+CR+W": 1468, "M+CR": 998}, "110336": {"PerTested": 0.605, "CR": 521, "Writing": 500, "NumTested": 101, "Math": 539, "M+CR+W": 1560, "M+CR": 1060}, "520320": {"PerTested": 0.38299999999999995, "CR": 444, "Writing": 421, "NumTested": 23, "Math": 458, "M+CR+W": 1323, "M+CR": 902}, "110340": {"PerTested": 0.41, "CR": 483, "Writing": 456, "NumTested": 94, "Math": 509, "M+CR+W": 1448, "M+CR": 992}, "920428": {"PerTested": 0.583, "CR": 503, "Writing": 481, "NumTested": 228, "Math": 524, "M+CR+W": 1508, "M+CR": 1027}, "280330": {"PerTested": 0.816, "CR": 504, "Writing": 488, "NumTested": 168, "Math": 525, "M+CR+W": 1517, "M+CR": 1029}, "450316": {"PerTested": 0.39799999999999996, "CR": 523, "Writing": 506, "NumTested": 96, "Math": 550, "M+CR+W": 1579, "M+CR": 1073}, "990990": {"PerTested": 0.446, "CR": 483, "Writing": 470, "NumTested": 169, "Math": 501, "M+CR+W": 1454, "M+CR": 984}, "580368": {"PerTested": 0.49200000000000005, "CR": 437, "Writing": 435, "NumTested": 62, "Math": 473, "M+CR+W": 1345, "M+CR": 910}, "510368": {"PerTested": 0.331, "CR": 479, "Writing": 477, "NumTested": 48, "Math": 544, "M+CR+W": 1500, "M+CR": 1023}, "500500": {"PerTested": 0.556, "CR": 488, "Writing": 461, "NumTested": 120, "Math": 496, "M+CR+W": 1445, "M+CR": 984}, "410390": {"PerTested": 0.807, "CR": 461, "Writing": 458, "NumTested": 46, "Math": 460, "M+CR+W": 1379, "M+CR": 921}, "230361": {"PerTested": 0.597, "CR": 486, "Writing": 475, "NumTested": 111, "Math": 500, "M+CR+W": 1461, "M+CR": 986}, "410394": {"PerTested": 0.708, "CR": 544, "Writing": 539, "NumTested": 281, "Math": 557, "M+CR+W": 1640, "M+CR": 1101}, "410395": {"PerTested": 1.02, "CR": 640, "Writing": 628, "NumTested": 50, "Math": 639, "M+CR+W": 1907, "M+CR": 1279}, "620316": {"PerTested": 0.5579999999999999, "CR": 404, "Writing": 393, "NumTested": 72, "Math": 422, "M+CR+W": 1219, "M+CR": 826}, "450334": {"PerTested": 0.685, "CR": 527, "Writing": 519, "NumTested": 100, "Math": 550, "M+CR+W": 1596, "M+CR": 1077}, "410399": {"PerTested": 0.222, "CR": 512, "Writing": 460, "NumTested": 6, "Math": 492, "M+CR+W": 1464, "M+CR": 1004}, "150304": {"PerTested": 0.588, "CR": 476, "Writing": 458, "NumTested": 77, "Math": 490, "M+CR+W": 1424, "M+CR": 966}, "410401": {"PerTested": 0.375, "CR": 473, "Writing": 441, "NumTested": 12, "Math": 473, "M+CR+W": 1387, "M+CR": 946}, "900900": {"PerTested": 0.6779999999999999, "CR": 499, "Writing": 489, "NumTested": 1292, "Math": 524, "M+CR+W": 1512, "M+CR": 1023}, "450341": {"PerTested": 0.491, "CR": 489, "Writing": 475, "NumTested": 85, "Math": 520, "M+CR+W": 1484, "M+CR": 1009}, "410406": {"PerTested": 0.667, "CR": 481, "Writing": 478, "NumTested": 168, "Math": 497, "M+CR+W": 1456, "M+CR": 978}, "410407": {"PerTested": 0.24, "CR": 422, "Writing": 392, "NumTested": 6, "Math": 412, "M+CR+W": 1226, "M+CR": 834}, "410408": {"PerTested": 0.289, "CR": 457, "Writing": 414, "NumTested": 11, "Math": 459, "M+CR+W": 1330, "M+CR": 916}, "410410": {"PerTested": 0.65, "CR": 488, "Writing": 480, "NumTested": 2984, "Math": 503, "M+CR+W": 1471, "M+CR": 991}, "110380": {"PerTested": 0.515, "CR": 517, "Writing": 507, "NumTested": 101, "Math": 552, "M+CR+W": 1576, "M+CR": 1069}, "450352": {"PerTested": 0.585, "CR": 523, "Writing": 493, "NumTested": 141, "Math": 534, "M+CR+W": 1550, "M+CR": 1057}, "370312": {"PerTested": 0.4, "CR": 465, "Writing": 455, "NumTested": 54, "Math": 495, "M+CR+W": 1415, "M+CR": 960}, "620340": {"PerTested": 0.489, "CR": 442, "Writing": 427, "NumTested": 67, "Math": 469, "M+CR+W": 1338, "M+CR": 911}, "320309": {"PerTested": 0.7190000000000001, "CR": 440, "Writing": 445, "NumTested": 46, "Math": 462, "M+CR+W": 1347, "M+CR": 902}, "320312": {"PerTested": 0.8340000000000001, "CR": 538, "Writing": 524, "NumTested": 277, "Math": 531, "M+CR+W": 1593, "M+CR": 1069}, "810810": {"PerTested": 0.44299999999999995, "CR": 463, "Writing": 452, "NumTested": 282, "Math": 483, "M+CR+W": 1398, "M+CR": 946}, "320320": {"PerTested": 0.684, "CR": 483, "Writing": 469, "NumTested": 1314, "Math": 484, "M+CR+W": 1436, "M+CR": 967}, "980318": {"PerTested": 0.369, "CR": 420, "Writing": 410, "NumTested": 66, "Math": 451, "M+CR+W": 1281, "M+CR": 871}, "320323": {"PerTested": 0.8640000000000001, "CR": 538, "Writing": 518, "NumTested": 153, "Math": 519, "M+CR+W": 1575, "M+CR": 1057}, "960324": {"PerTested": 0.546, "CR": 505, "Writing": 481, "NumTested": 124, "Math": 512, "M+CR+W": 1498, "M+CR": 1017}, "320325": {"PerTested": 0.65, "CR": 427, "Writing": 416, "NumTested": 180, "Math": 427, "M+CR+W": 1270, "M+CR": 854}, "630360": {"PerTested": 0.491, "CR": 493, "Writing": 477, "NumTested": 156, "Math": 520, "M+CR+W": 1490, "M+CR": 1013}, "840332": {"PerTested": 0.43799999999999994, "CR": 457, "Writing": 453, "NumTested": 71, "Math": 477, "M+CR+W": 1387, "M+CR": 934}, "960330": {"PerTested": 0.604, "CR": 497, "Writing": 476, "NumTested": 162, "Math": 521, "M+CR+W": 1494, "M+CR": 1018}, "270306": {"PerTested": 0.561, "CR": 485, "Writing": 472, "NumTested": 160, "Math": 508, "M+CR+W": 1465, "M+CR": 993}, "20302": {"PerTested": 0.48100000000000004, "CR": 466, "Writing": 443, "NumTested": 163, "Math": 487, "M+CR+W": 1396, "M+CR": 953}, "821308": {"PerTested": 0.544, "CR": 458, "Writing": 454, "NumTested": 86, "Math": 484, "M+CR+W": 1396, "M+CR": 942}, "110416": {"PerTested": 0.738, "CR": 538, "Writing": 533, "NumTested": 217, "Math": 562, "M+CR+W": 1633, "M+CR": 1100}, "260408": {"PerTested": 0.622, "CR": 460, "Writing": 439, "NumTested": 201, "Math": 462, "M+CR+W": 1361, "M+CR": 922}, "790354": {"PerTested": 0.552, "CR": 478, "Writing": 462, "NumTested": 123, "Math": 505, "M+CR+W": 1445, "M+CR": 983}, "410595": {"PerTested": 0.774, "CR": 515, "Writing": 513, "NumTested": 274, "Math": 530, "M+CR+W": 1558, "M+CR": 1045}, "820820": {"PerTested": 0.469, "CR": 438, "Writing": 426, "NumTested": 197, "Math": 466, "M+CR+W": 1330, "M+CR": 904}, "940308": {"PerTested": 0.25, "CR": 376, "Writing": 410, "NumTested": 5, "Math": 448, "M+CR+W": 1234, "M+CR": 824}, "230230": {"PerTested": 0.511, "CR": 482, "Writing": 465, "NumTested": 492, "Math": 504, "M+CR+W": 1451, "M+CR": 986}, "600377": {"PerTested": 0.687, "CR": 507, "Writing": 491, "NumTested": 268, "Math": 518, "M+CR+W": 1516, "M+CR": 1025}, "580580": {"PerTested": 0.465, "CR": 447, "Writing": 434, "NumTested": 131, "Math": 489, "M+CR+W": 1370, "M+CR": 936}, "920412": {"PerTested": 0.782, "CR": 580, "Writing": 574, "NumTested": 445, "Math": 594, "M+CR+W": 1748, "M+CR": 1174}, "790366": {"PerTested": 0.588, "CR": 452, "Writing": 437, "NumTested": 90, "Math": 440, "M+CR+W": 1329, "M+CR": 892}, "490335": {"PerTested": 0.82, "CR": 532, "Writing": 507, "NumTested": 310, "Math": 555, "M+CR+W": 1594, "M+CR": 1087}, "590330": {"PerTested": 0.40399999999999997, "CR": 492, "Writing": 470, "NumTested": 157, "Math": 506, "M+CR+W": 1468, "M+CR": 998}, "820388": {"PerTested": 0.425, "CR": 430, "Writing": 412, "NumTested": 37, "Math": 446, "M+CR+W": 1288, "M+CR": 876}, "320356": {"PerTested": 0.698, "CR": 447, "Writing": 435, "NumTested": 217, "Math": 464, "M+CR+W": 1346, "M+CR": 911}, "630630": {"PerTested": 0.517, "CR": 503, "Writing": 489, "NumTested": 465, "Math": 536, "M+CR+W": 1528, "M+CR": 1039}, "490346": {"PerTested": 0.46399999999999997, "CR": 496, "Writing": 481, "NumTested": 91, "Math": 525, "M+CR+W": 1502, "M+CR": 1021}, "140140": {"PerTested": 0.41100000000000003, "CR": 490, "Writing": 478, "NumTested": 315, "Math": 519, "M+CR+W": 1487, "M+CR": 1009}, "320365": {"PerTested": 0.7, "CR": 499, "Writing": 482, "NumTested": 261, "Math": 510, "M+CR+W": 1491, "M+CR": 1009}, "320368": {"PerTested": 0.485, "CR": 423, "Writing": 407, "NumTested": 150, "Math": 419, "M+CR+W": 1249, "M+CR": 842}, "670324": {"PerTested": 0.623, "CR": 471, "Writing": 447, "NumTested": 157, "Math": 496, "M+CR+W": 1414, "M+CR": 967}, "490354": {"PerTested": 0.408, "CR": 504, "Writing": 489, "NumTested": 98, "Math": 544, "M+CR+W": 1537, "M+CR": 1048}, "410483": {"PerTested": 0.579, "CR": 346, "Writing": 323, "NumTested": 11, "Math": 335, "M+CR+W": 1004, "M+CR": 681}, "410484": {"PerTested": 0.556, "CR": 449, "Writing": 431, "NumTested": 144, "Math": 459, "M+CR+W": 1339, "M+CR": 908}, "360310": {"PerTested": 0.5660000000000001, "CR": 491, "Writing": 473, "NumTested": 168, "Math": 500, "M+CR+W": 1464, "M+CR": 991}, "920441": {"PerTested": 0.91, "CR": 546, "Writing": 543, "NumTested": 488, "Math": 588, "M+CR+W": 1677, "M+CR": 1134}, "490362": {"PerTested": 0.444, "CR": 498, "Writing": 476, "NumTested": 84, "Math": 545, "M+CR+W": 1519, "M+CR": 1043}, "920500": {"PerTested": 0.7859999999999999, "CR": 490, "Writing": 480, "NumTested": 337, "Math": 512, "M+CR+W": 1482, "M+CR": 1002}, "540540": {"PerTested": 0.39299999999999996, "CR": 465, "Writing": 452, "NumTested": 234, "Math": 494, "M+CR+W": 1411, "M+CR": 959}, "821821": {"PerTested": 0.544, "CR": 458, "Writing": 454, "NumTested": 86, "Math": 484, "M+CR+W": 1396, "M+CR": 942}, "190336": {"PerTested": 0.486, "CR": 481, "Writing": 463, "NumTested": 84, "Math": 492, "M+CR+W": 1436, "M+CR": 973}, "750318": {"PerTested": 0.556, "CR": 513, "Writing": 492, "NumTested": 85, "Math": 523, "M+CR+W": 1528, "M+CR": 1036}, "9090": {"PerTested": 0.531, "CR": 421, "Writing": 405, "NumTested": 161, "Math": 435, "M+CR+W": 1261, "M+CR": 856}, "970390": {"PerTested": 0.62, "CR": 506, "Writing": 474, "NumTested": 106, "Math": 527, "M+CR+W": 1507, "M+CR": 1033}, "190342": {"PerTested": 0.679, "CR": 503, "Writing": 493, "NumTested": 146, "Math": 512, "M+CR+W": 1508, "M+CR": 1015}, "780780": {"PerTested": 0.387, "CR": 426, "Writing": 418, "NumTested": 500, "Math": 454, "M+CR+W": 1298, "M+CR": 880}, "830346": {"PerTested": 0.5770000000000001, "CR": 451, "Writing": 441, "NumTested": 214, "Math": 481, "M+CR+W": 1373, "M+CR": 932}, "490380": {"PerTested": 0.40700000000000003, "CR": 484, "Writing": 466, "NumTested": 72, "Math": 512, "M+CR+W": 1462, "M+CR": 996}, "60302": {"PerTested": 0.508, "CR": 487, "Writing": 456, "NumTested": 61, "Math": 505, "M+CR+W": 1448, "M+CR": 992}, "8080": {"PerTested": 0.505, "CR": 408, "Writing": 403, "NumTested": 104, "Math": 424, "M+CR+W": 1235, "M+CR": 832}, "450450": {"PerTested": 0.524, "CR": 517, "Writing": 498, "NumTested": 422, "Math": 538, "M+CR+W": 1553, "M+CR": 1055}, "920473": {"PerTested": 0.853, "CR": 525, "Writing": 517, "NumTested": 405, "Math": 555, "M+CR+W": 1597, "M+CR": 1080}, "700317": {"PerTested": 0.69, "CR": 453, "Writing": 443, "NumTested": 136, "Math": 456, "M+CR+W": 1352, "M+CR": 909}, "7070": {"PerTested": 0.47100000000000003, "CR": 475, "Writing": 461, "NumTested": 179, "Math": 505, "M+CR+W": 1441, "M+CR": 980}, "491312": {"PerTested": 0.629, "CR": 492, "Writing": 479, "NumTested": 229, "Math": 513, "M+CR+W": 1484, "M+CR": 1005}, "530336": {"PerTested": 0.627, "CR": 478, "Writing": 461, "NumTested": 178, "Math": 506, "M+CR+W": 1445, "M+CR": 984}, "410529": {"PerTested": 0.68, "CR": 487, "Writing": 487, "NumTested": 198, "Math": 508, "M+CR+W": 1482, "M+CR": 995}, "850850": {"PerTested": 0.441, "CR": 487, "Writing": 477, "NumTested": 215, "Math": 510, "M+CR+W": 1474, "M+CR": 997}, "995995": {"PerTested": 0.43200000000000005, "CR": 512, "Writing": 482, "NumTested": 63, "Math": 523, "M+CR+W": 1517, "M+CR": 1035}, "182182": {"PerTested": 0.642, "CR": 474, "Writing": 456, "NumTested": 138, "Math": 507, "M+CR+W": 1437, "M+CR": 981}, "530343": {"PerTested": 0.455, "CR": 465, "Writing": 446, "NumTested": 92, "Math": 493, "M+CR+W": 1404, "M+CR": 958}, "230312": {"PerTested": 0.489, "CR": 457, "Writing": 445, "NumTested": 112, "Math": 481, "M+CR+W": 1383, "M+CR": 938}, "860316": {"PerTested": 0.47700000000000004, "CR": 499, "Writing": 481, "NumTested": 71, "Math": 525, "M+CR+W": 1505, "M+CR": 1024}, "870314": {"PerTested": 0.467, "CR": 496, "Writing": 482, "NumTested": 49, "Math": 504, "M+CR+W": 1482, "M+CR": 1000}, "6060": {"PerTested": 0.508, "CR": 487, "Writing": 456, "NumTested": 61, "Math": 505, "M+CR+W": 1448, "M+CR": 992}, "920562": {"PerTested": 0.732, "CR": 492, "Writing": 479, "NumTested": 339, "Math": 504, "M+CR+W": 1475, "M+CR": 996}, "920495": {"PerTested": 0.69, "CR": 520, "Writing": 497, "NumTested": 327, "Math": 529, "M+CR+W": 1546, "M+CR": 1049}, "410544": {"PerTested": 0.495, "CR": 408, "Writing": 398, "NumTested": 137, "Math": 437, "M+CR+W": 1243, "M+CR": 845}, "410545": {"PerTested": 0.652, "CR": 396, "Writing": 387, "NumTested": 30, "Math": 416, "M+CR+W": 1199, "M+CR": 812}, "410547": {"PerTested": 0.6990000000000001, "CR": 474, "Writing": 460, "NumTested": 209, "Math": 490, "M+CR+W": 1424, "M+CR": 964}, "230324": {"PerTested": 0.507, "CR": 493, "Writing": 467, "NumTested": 151, "Math": 511, "M+CR+W": 1471, "M+CR": 1004}, "760760": {"PerTested": 0.46799999999999997, "CR": 481, "Writing": 466, "NumTested": 482, "Math": 504, "M+CR+W": 1451, "M+CR": 985}, "5050": {"PerTested": 0.503, "CR": 502, "Writing": 473, "NumTested": 93, "Math": 530, "M+CR+W": 1505, "M+CR": 1032}, "410556": {"PerTested": 0.506, "CR": 441, "Writing": 429, "NumTested": 119, "Math": 448, "M+CR+W": 1318, "M+CR": 889}, "181181": {"PerTested": 0.738, "CR": 508, "Writing": 499, "NumTested": 200, "Math": 534, "M+CR+W": 1541, "M+CR": 1042}, "270270": {"PerTested": 0.561, "CR": 485, "Writing": 472, "NumTested": 160, "Math": 508, "M+CR+W": 1465, "M+CR": 993}, "410562": {"PerTested": 0.7, "CR": 476, "Writing": 462, "NumTested": 194, "Math": 494, "M+CR+W": 1432, "M+CR": 970}, "360390": {"PerTested": 0.541, "CR": 461, "Writing": 456, "NumTested": 140, "Math": 486, "M+CR+W": 1403, "M+CR": 947}, "4040": {"PerTested": 0.44299999999999995, "CR": 409, "Writing": 406, "NumTested": 97, "Math": 434, "M+CR+W": 1249, "M+CR": 843}, "600396": {"PerTested": 0.507, "CR": 425, "Writing": 407, "NumTested": 113, "Math": 426, "M+CR+W": 1258, "M+CR": 851}, "360396": {"PerTested": 0.6609999999999999, "CR": 481, "Writing": 468, "NumTested": 179, "Math": 500, "M+CR+W": 1449, "M+CR": 981}, "570318": {"PerTested": 0.466, "CR": 486, "Writing": 466, "NumTested": 61, "Math": 505, "M+CR+W": 1457, "M+CR": 991}, "920528": {"PerTested": 0.096, "CR": 360, "Writing": 362, "NumTested": 5, "Math": 372, "M+CR+W": 1094, "M+CR": 732}, "180180": {"PerTested": 0.5760000000000001, "CR": 487, "Writing": 471, "NumTested": 602, "Math": 526, "M+CR+W": 1484, "M+CR": 1013}, "740309": {"PerTested": 0.451, "CR": 486, "Writing": 451, "NumTested": 60, "Math": 495, "M+CR+W": 1432, "M+CR": 981}, "3030": {"PerTested": 0.43700000000000006, "CR": 480, "Writing": 464, "NumTested": 52, "Math": 519, "M+CR+W": 1463, "M+CR": 999}, "440440": {"PerTested": 0.498, "CR": 511, "Writing": 503, "NumTested": 236, "Math": 547, "M+CR+W": 1561, "M+CR": 1058}, "960335": {"PerTested": 0.547, "CR": 418, "Writing": 392, "NumTested": 75, "Math": 417, "M+CR+W": 1227, "M+CR": 835}, "410589": {"PerTested": 0.938, "CR": 563, "Writing": 530, "NumTested": 60, "Math": 545, "M+CR+W": 1638, "M+CR": 1108}, "760380": {"PerTested": 0.514, "CR": 485, "Writing": 474, "NumTested": 147, "Math": 505, "M+CR+W": 1464, "M+CR": 990}, "720720": {"PerTested": 0.51, "CR": 456, "Writing": 423, "NumTested": 53, "Math": 480, "M+CR+W": 1359, "M+CR": 936}, "360418": {"PerTested": 0.8640000000000001, "CR": 492, "Writing": 474, "NumTested": 114, "Math": 518, "M+CR+W": 1484, "M+CR": 1010}, "491491": {"PerTested": 0.629, "CR": 492, "Writing": 479, "NumTested": 229, "Math": 513, "M+CR+W": 1484, "M+CR": 1005}, "2020": {"PerTested": 0.48100000000000004, "CR": 466, "Writing": 443, "NumTested": 163, "Math": 487, "M+CR+W": 1396, "M+CR": 953}, "100326": {"PerTested": 0.321, "CR": 464, "Writing": 458, "NumTested": 59, "Math": 480, "M+CR+W": 1402, "M+CR": 944}, "960372": {"PerTested": 0.382, "CR": 495, "Writing": 462, "NumTested": 55, "Math": 502, "M+CR+W": 1459, "M+CR": 997}, "340568": {"PerTested": 0.794, "CR": 450, "Writing": 435, "NumTested": 54, "Math": 434, "M+CR+W": 1319, "M+CR": 884}, "960490": {"PerTested": 0.29, "CR": 581, "Writing": 557, "NumTested": 9, "Math": 551, "M+CR+W": 1689, "M+CR": 1132}, "360428": {"PerTested": 0.349, "CR": 452, "Writing": 441, "NumTested": 73, "Math": 458, "M+CR+W": 1351, "M+CR": 910}, "740333": {"PerTested": 0.5579999999999999, "CR": 499, "Writing": 490, "NumTested": 164, "Math": 526, "M+CR+W": 1515, "M+CR": 1025}, "100334": {"PerTested": 0.48700000000000004, "CR": 513, "Writing": 495, "NumTested": 110, "Math": 519, "M+CR+W": 1527, "M+CR": 1032}, "1010": {"PerTested": 0.621, "CR": 481, "Writing": 467, "NumTested": 821, "Math": 508, "M+CR+W": 1456, "M+CR": 989}, "600496": {"PerTested": 0.7659999999999999, "CR": 414, "Writing": 398, "NumTested": 193, "Math": 422, "M+CR+W": 1234, "M+CR": 836}, "980980": {"PerTested": 0.466, "CR": 470, "Writing": 459, "NumTested": 311, "Math": 494, "M+CR+W": 1423, "M+CR": 964}, "760318": {"PerTested": 0.46299999999999997, "CR": 479, "Writing": 463, "NumTested": 132, "Math": 505, "M+CR+W": 1447, "M+CR": 984}, "740344": {"PerTested": 0.5920000000000001, "CR": 453, "Writing": 449, "NumTested": 90, "Math": 484, "M+CR+W": 1386, "M+CR": 937}, "920436": {"PerTested": 0.509, "CR": 461, "Writing": 440, "NumTested": 217, "Math": 471, "M+CR+W": 1372, "M+CR": 932}, "490490": {"PerTested": 0.55, "CR": 513, "Writing": 492, "NumTested": 655, "Math": 543, "M+CR+W": 1548, "M+CR": 1056}, "400308": {"PerTested": 0.515, "CR": 459, "Writing": 445, "NumTested": 87, "Math": 474, "M+CR+W": 1378, "M+CR": 933}, "100348": {"PerTested": 0.46, "CR": 494, "Writing": 476, "NumTested": 114, "Math": 507, "M+CR+W": 1477, "M+CR": 1001}, "520520": {"PerTested": 0.38299999999999995, "CR": 444, "Writing": 421, "NumTested": 23, "Math": 458, "M+CR+W": 1323, "M+CR": 902}, "920368": {"PerTested": 0.747, "CR": 529, "Writing": 511, "NumTested": 384, "Math": 558, "M+CR+W": 1598, "M+CR": 1087}}