{"600576": {"PerTested": 0.509, "CR": 420, "Writing": 397, "NumTested": 164, "Math": 426, "M+CR+W": 1243, "M+CR": 846}, "995330": {"PerTested": 0.511, "CR": 504, "Writing": 483, "NumTested": 72, "Math": 538, "M+CR+W": 1525, "M+CR": 1042}, "940316": {"PerTested": 0.519, "CR": 401, "Writing": 395, "NumTested": 55, "Math": 420, "M+CR+W": 1216, "M+CR": 821}, "920583": {"PerTested": 0.893, "CR": 506, "Writing": 500, "NumTested": 50, "Math": 496, "M+CR+W": 1502, "M+CR": 1002}, "670670": {"PerTested": 0.613, "CR": 479, "Writing": 454, "NumTested": 785, "Math": 497, "M+CR+W": 1430, "M+CR": 976}, "970356": {"PerTested": 0.355, "CR": 500, "Writing": 474, "NumTested": 44, "Math": 519, "M+CR+W": 1493, "M+CR": 1019}, "890890": {"PerTested": 0.455, "CR": 423, "Writing": 396, "NumTested": 15, "Math": 443, "M+CR+W": 1262, "M+CR": 866}, "920588": {"PerTested": 0.7170000000000001, "CR": 502, "Writing": 478, "NumTested": 302, "Math": 515, "M+CR+W": 1495, "M+CR": 1017}, "740366": {"PerTested": 0.7040000000000001, "CR": 529, "Writing": 512, "NumTested": 221, "Math": 548, "M+CR+W": 1589, "M+CR": 1077}, "400400": {"PerTested": 0.387, "CR": 419, "Writing": 392, "NumTested": 82, "Math": 433, "M+CR+W": 1244, "M+CR": 852}, "140305": {"PerTested": 0.304, "CR": 476, "Writing": 427, "NumTested": 7, "Math": 463, "M+CR+W": 1366, "M+CR": 939}, "920595": {"PerTested": 0.875, "CR": 505, "Writing": 486, "NumTested": 517, "Math": 523, "M+CR+W": 1514, "M+CR": 1028}, "140309": {"PerTested": 0.45899999999999996, "CR": 514, "Writing": 491, "NumTested": 61, "Math": 526, "M+CR+W": 1531, "M+CR": 1040}, "360470": {"PerTested": 0.382, "CR": 478, "Writing": 449, "NumTested": 76, "Math": 518, "M+CR+W": 1445, "M+CR": 996}, "650340": {"PerTested": 0.862, "CR": 548, "Writing": 514, "NumTested": 50, "Math": 559, "M+CR+W": 1621, "M+CR": 1107}, "970970": {"PerTested": 0.503, "CR": 498, "Writing": 473, "NumTested": 268, "Math": 521, "M+CR+W": 1492, "M+CR": 1019}, "290308": {"PerTested": 0.508, "CR": 473, "Writing": 443, "NumTested": 100, "Math": 493, "M+CR+W": 1409, "M+CR": 966}, "440346": {"PerTested": 0.20800000000000002, "CR": 542, "Writing": 486, "NumTested": 10, "Math": 509, "M+CR+W": 1537, "M+CR": 1051}, "910364": {"PerTested": 0.537, "CR": 403, "Writing": 399, "NumTested": 95, "Math": 444, "M+CR+W": 1246, "M+CR": 847}, "610334": {"PerTested": 0.622, "CR": 494, "Writing": 447, "NumTested": 79, "Math": 485, "M+CR+W": 1426, "M+CR": 979}, "800800": {"PerTested": 0.519, "CR": 474, "Writing": 453, "NumTested": 676, "Math": 495, "M+CR+W": 1422, "M+CR": 969}, "840368": {"PerTested": 0.517, "CR": 490, "Writing": 468, "NumTested": 108, "Math": 524, "M+CR+W": 1482, "M+CR": 1014}, "910370": {"PerTested": 0.452, "CR": 432, "Writing": 412, "NumTested": 104, "Math": 453, "M+CR+W": 1297, "M+CR": 885}, "920700": {"PerTested": 0.45799999999999996, "CR": 415, "Writing": 426, "NumTested": 33, "Math": 472, "M+CR+W": 1313, "M+CR": 887}, "132132": {"PerTested": 0.513, "CR": 465, "Writing": 444, "NumTested": 134, "Math": 473, "M+CR+W": 1382, "M+CR": 938}, "420358": {"PerTested": 0.455, "CR": 386, "Writing": 375, "NumTested": 51, "Math": 375, "M+CR+W": 1136, "M+CR": 761}, "310310": {"PerTested": 0.435, "CR": 447, "Writing": 435, "NumTested": 195, "Math": 462, "M+CR+W": 1344, "M+CR": 909}, "920526": {"PerTested": 0.88, "CR": 543, "Writing": 530, "NumTested": 461, "Math": 564, "M+CR+W": 1637, "M+CR": 1107}, "182316": {"PerTested": 0.644, "CR": 473, "Writing": 456, "NumTested": 114, "Math": 505, "M+CR+W": 1434, "M+CR": 978}, "360494": {"PerTested": 0.674, "CR": 487, "Writing": 468, "NumTested": 211, "Math": 495, "M+CR+W": 1450, "M+CR": 982}, "291336": {"PerTested": 0.561, "CR": 445, "Writing": 421, "NumTested": 83, "Math": 454, "M+CR+W": 1320, "M+CR": 899}, "480307": {"PerTested": 0.47200000000000003, "CR": 417, "Writing": 393, "NumTested": 17, "Math": 429, "M+CR+W": 1239, "M+CR": 846}, "260446": {"PerTested": 0.67, "CR": 503, "Writing": 493, "NumTested": 201, "Math": 522, "M+CR+W": 1518, "M+CR": 1025}, "710710": {"PerTested": 0.541, "CR": 480, "Writing": 456, "NumTested": 318, "Math": 489, "M+CR+W": 1425, "M+CR": 969}, "660660": {"PerTested": 0.795, "CR": 374, "Writing": 370, "NumTested": 124, "Math": 403, "M+CR+W": 1147, "M+CR": 777}, "440378": {"PerTested": 0.46299999999999997, "CR": 480, "Writing": 471, "NumTested": 93, "Math": 512, "M+CR+W": 1463, "M+CR": 992}, "140348": {"PerTested": 0.583, "CR": 469, "Writing": 468, "NumTested": 123, "Math": 493, "M+CR+W": 1430, "M+CR": 962}, "10303": {"PerTested": 0.4, "CR": 452, "Writing": 421, "NumTested": 10, "Math": 483, "M+CR+W": 1356, "M+CR": 935}, "950336": {"PerTested": 0.7909999999999999, "CR": 540, "Writing": 506, "NumTested": 216, "Math": 544, "M+CR+W": 1590, "M+CR": 1084}, "310338": {"PerTested": 0.78, "CR": 441, "Writing": 426, "NumTested": 32, "Math": 438, "M+CR+W": 1305, "M+CR": 879}, "440390": {"PerTested": 0.5670000000000001, "CR": 530, "Writing": 510, "NumTested": 132, "Math": 553, "M+CR+W": 1593, "M+CR": 1083}, "310344": {"PerTested": 0.35100000000000003, "CR": 487, "Writing": 484, "NumTested": 59, "Math": 515, "M+CR+W": 1486, "M+CR": 1002}, "181322": {"PerTested": 0.7140000000000001, "CR": 514, "Writing": 501, "NumTested": 155, "Math": 536, "M+CR+W": 1551, "M+CR": 1050}, "620620": {"PerTested": 0.433, "CR": 418, "Writing": 417, "NumTested": 110, "Math": 446, "M+CR+W": 1281, "M+CR": 864}, "310352": {"PerTested": 0.43799999999999994, "CR": 397, "Writing": 377, "NumTested": 35, "Math": 403, "M+CR+W": 1177, "M+CR": 800}, "130130": {"PerTested": 0.653, "CR": 497, "Writing": 483, "NumTested": 1169, "Math": 522, "M+CR+W": 1502, "M+CR": 1019}, "10324": {"PerTested": 0.7090000000000001, "CR": 480, "Writing": 451, "NumTested": 146, "Math": 517, "M+CR+W": 1448, "M+CR": 997}, "650326": {"PerTested": 0.59, "CR": 481, "Writing": 466, "NumTested": 214, "Math": 494, "M+CR+W": 1441, "M+CR": 975}, "650327": {"PerTested": 0.616, "CR": 512, "Writing": 486, "NumTested": 188, "Math": 523, "M+CR+W": 1521, "M+CR": 1035}, "310364": {"PerTested": 0.552, "CR": 447, "Writing": 435, "NumTested": 37, "Math": 474, "M+CR+W": 1356, "M+CR": 921}, "180320": {"PerTested": 0.473, "CR": 458, "Writing": 425, "NumTested": 89, "Math": 496, "M+CR+W": 1379, "M+CR": 954}, "600592": {"PerTested": 0.526, "CR": 433, "Writing": 416, "NumTested": 205, "Math": 441, "M+CR+W": 1290, "M+CR": 874}, "530530": {"PerTested": 0.562, "CR": 476, "Writing": 448, "NumTested": 313, "Math": 497, "M+CR+W": 1421, "M+CR": 973}, "350308": {"PerTested": 0.626, "CR": 485, "Writing": 461, "NumTested": 97, "Math": 506, "M+CR+W": 1452, "M+CR": 991}, "180325": {"PerTested": 0.758, "CR": 505, "Writing": 477, "NumTested": 72, "Math": 517, "M+CR+W": 1499, "M+CR": 1022}, "140390": {"PerTested": 0.603, "CR": 450, "Writing": 425, "NumTested": 117, "Math": 476, "M+CR+W": 1351, "M+CR": 926}, "780391": {"PerTested": 0.311, "CR": 387, "Writing": 384, "NumTested": 46, "Math": 415, "M+CR+W": 1186, "M+CR": 802}, "862312": {"PerTested": 0.547, "CR": 487, "Writing": 473, "NumTested": 58, "Math": 527, "M+CR+W": 1487, "M+CR": 1014}, "960700": {"PerTested": 0.69, "CR": 472, "Writing": 443, "NumTested": 40, "Math": 505, "M+CR+W": 1420, "M+CR": 977}, "10348": {"PerTested": 0.5479999999999999, "CR": 439, "Writing": 423, "NumTested": 86, "Math": 463, "M+CR+W": 1325, "M+CR": 902}, "800340": {"PerTested": 0.469, "CR": 494, "Writing": 465, "NumTested": 135, "Math": 514, "M+CR+W": 1473, "M+CR": 1008}, "650352": {"PerTested": 0.7120000000000001, "CR": 491, "Writing": 464, "NumTested": 232, "Math": 506, "M+CR+W": 1461, "M+CR": 997}, "350321": {"PerTested": 0.537, "CR": 475, "Writing": 469, "NumTested": 87, "Math": 485, "M+CR+W": 1429, "M+CR": 960}, "780402": {"PerTested": 0.38299999999999995, "CR": 371, "Writing": 349, "NumTested": 41, "Math": 410, "M+CR+W": 1130, "M+CR": 781}, "760339": {"PerTested": 0.583, "CR": 487, "Writing": 461, "NumTested": 91, "Math": 516, "M+CR+W": 1464, "M+CR": 1003}, "180340": {"PerTested": 0.5429999999999999, "CR": 488, "Writing": 461, "NumTested": 133, "Math": 525, "M+CR+W": 1474, "M+CR": 1013}, "990326": {"PerTested": 0.446, "CR": 486, "Writing": 463, "NumTested": 70, "Math": 510, "M+CR+W": 1459, "M+CR": 996}, "640361": {"PerTested": 0.5539999999999999, "CR": 456, "Writing": 444, "NumTested": 134, "Math": 493, "M+CR+W": 1393, "M+CR": 949}, "310392": {"PerTested": 0.348, "CR": 431, "Writing": 417, "NumTested": 32, "Math": 439, "M+CR+W": 1287, "M+CR": 870}, "180348": {"PerTested": 0.486, "CR": 455, "Writing": 436, "NumTested": 89, "Math": 501, "M+CR+W": 1392, "M+CR": 956}, "340330": {"PerTested": 0.6409999999999999, "CR": 402, "Writing": 391, "NumTested": 75, "Math": 416, "M+CR+W": 1209, "M+CR": 818}, "50302": {"PerTested": 0.56, "CR": 483, "Writing": 466, "NumTested": 116, "Math": 522, "M+CR+W": 1471, "M+CR": 1005}, "920703": {"PerTested": 0.293, "CR": 461, "Writing": 437, "NumTested": 22, "Math": 512, "M+CR+W": 1410, "M+CR": 973}, "350336": {"PerTested": 0.429, "CR": 447, "Writing": 424, "NumTested": 75, "Math": 464, "M+CR+W": 1335, "M+CR": 911}, "860352": {"PerTested": 0.426, "CR": 473, "Writing": 444, "NumTested": 58, "Math": 512, "M+CR+W": 1429, "M+CR": 985}, "780420": {"PerTested": 0.389, "CR": 411, "Writing": 398, "NumTested": 136, "Math": 459, "M+CR+W": 1268, "M+CR": 870}, "740374": {"PerTested": 0.45299999999999996, "CR": 421, "Writing": 397, "NumTested": 81, "Math": 437, "M+CR+W": 1255, "M+CR": 858}, "780401": {"PerTested": 0.214, "CR": 426, "Writing": 402, "NumTested": 36, "Math": 470, "M+CR+W": 1298, "M+CR": 896}, "840840": {"PerTested": 0.57, "CR": 465, "Writing": 442, "NumTested": 339, "Math": 495, "M+CR+W": 1402, "M+CR": 960}, "190316": {"PerTested": 0.6559999999999999, "CR": 448, "Writing": 426, "NumTested": 61, "Math": 483, "M+CR+W": 1357, "M+CR": 931}, "350350": {"PerTested": 0.526, "CR": 471, "Writing": 453, "NumTested": 259, "Math": 487, "M+CR+W": 1411, "M+CR": 958}, "920441": {"PerTested": 0.9309999999999999, "CR": 550, "Writing": 544, "NumTested": 445, "Math": 593, "M+CR+W": 1687, "M+CR": 1143}, "690320": {"PerTested": 0.43200000000000005, "CR": 494, "Writing": 454, "NumTested": 41, "Math": 526, "M+CR+W": 1474, "M+CR": 1020}, "861861": {"PerTested": 0.6990000000000001, "CR": 507, "Writing": 478, "NumTested": 58, "Math": 521, "M+CR+W": 1506, "M+CR": 1028}, "10388": {"PerTested": 0.545, "CR": 460, "Writing": 446, "NumTested": 150, "Math": 485, "M+CR+W": 1391, "M+CR": 945}, "830830": {"PerTested": 0.639, "CR": 429, "Writing": 418, "NumTested": 202, "Math": 458, "M+CR+W": 1305, "M+CR": 887}, "220310": {"PerTested": 0.596, "CR": 494, "Writing": 492, "NumTested": 53, "Math": 524, "M+CR+W": 1510, "M+CR": 1018}, "180376": {"PerTested": 0.619, "CR": 514, "Writing": 484, "NumTested": 161, "Math": 530, "M+CR+W": 1528, "M+CR": 1044}, "650394": {"PerTested": 0.353, "CR": 488, "Writing": 448, "NumTested": 12, "Math": 472, "M+CR+W": 1408, "M+CR": 960}, "10396": {"PerTested": 0.732, "CR": 477, "Writing": 468, "NumTested": 153, "Math": 509, "M+CR+W": 1454, "M+CR": 986}, "750750": {"PerTested": 0.621, "CR": 487, "Writing": 459, "NumTested": 105, "Math": 508, "M+CR+W": 1454, "M+CR": 995}, "10400": {"PerTested": 0.6729999999999999, "CR": 493, "Writing": 485, "NumTested": 167, "Math": 530, "M+CR+W": 1508, "M+CR": 1023}, "660336": {"PerTested": 0.6920000000000001, "CR": 375, "Writing": 380, "NumTested": 63, "Math": 409, "M+CR+W": 1164, "M+CR": 784}, "260260": {"PerTested": 0.5589999999999999, "CR": 469, "Writing": 445, "NumTested": 1803, "Math": 476, "M+CR+W": 1390, "M+CR": 945}, "70342": {"PerTested": 0.563, "CR": 468, "Writing": 434, "NumTested": 111, "Math": 489, "M+CR+W": 1391, "M+CR": 957}, "150700": {"PerTested": 0.7709999999999999, "CR": 463, "Writing": 440, "NumTested": 27, "Math": 456, "M+CR+W": 1359, "M+CR": 919}, "860336": {"PerTested": 0.38799999999999996, "CR": 469, "Writing": 456, "NumTested": 71, "Math": 508, "M+CR+W": 1433, "M+CR": 977}, "390322": {"PerTested": 0.414, "CR": 458, "Writing": 431, "NumTested": 60, "Math": 461, "M+CR+W": 1350, "M+CR": 919}, "241316": {"PerTested": 0.619, "CR": 444, "Writing": 439, "NumTested": 78, "Math": 468, "M+CR+W": 1351, "M+CR": 912}, "390324": {"PerTested": 0.573, "CR": 457, "Writing": 447, "NumTested": 71, "Math": 488, "M+CR+W": 1392, "M+CR": 945}, "510324": {"PerTested": 0.605, "CR": 494, "Writing": 477, "NumTested": 257, "Math": 520, "M+CR+W": 1491, "M+CR": 1014}, "170170": {"PerTested": 0.565, "CR": 437, "Writing": 424, "NumTested": 91, "Math": 452, "M+CR+W": 1313, "M+CR": 889}, "320700": {"PerTested": 0.654, "CR": 397, "Writing": 381, "NumTested": 34, "Math": 410, "M+CR+W": 1188, "M+CR": 807}, "320701": {"PerTested": 0.953, "CR": 439, "Writing": 413, "NumTested": 82, "Math": 422, "M+CR+W": 1274, "M+CR": 861}, "560320": {"PerTested": 0.601, "CR": 484, "Writing": 454, "NumTested": 116, "Math": 493, "M+CR+W": 1431, "M+CR": 977}, "460320": {"PerTested": 0.635, "CR": 392, "Writing": 377, "NumTested": 141, "Math": 412, "M+CR+W": 1181, "M+CR": 804}, "860354": {"PerTested": 0.255, "CR": 537, "Writing": 520, "NumTested": 27, "Math": 510, "M+CR+W": 1567, "M+CR": 1047}, "560324": {"PerTested": 0.5710000000000001, "CR": 511, "Writing": 479, "NumTested": 16, "Math": 542, "M+CR+W": 1532, "M+CR": 1053}, "680310": {"PerTested": 0.82, "CR": 528, "Writing": 516, "NumTested": 159, "Math": 533, "M+CR+W": 1577, "M+CR": 1061}, "560329": {"PerTested": 0.5, "CR": 564, "Writing": 515, "NumTested": 13, "Math": 537, "M+CR+W": 1616, "M+CR": 1101}, "570570": {"PerTested": 0.392, "CR": 498, "Writing": 461, "NumTested": 58, "Math": 510, "M+CR+W": 1469, "M+CR": 1008}, "560332": {"PerTested": 0.75, "CR": 498, "Writing": 495, "NumTested": 6, "Math": 558, "M+CR+W": 1551, "M+CR": 1056}, "132304": {"PerTested": 0.513, "CR": 465, "Writing": 444, "NumTested": 134, "Math": 473, "M+CR+W": 1382, "M+CR": 938}, "861308": {"PerTested": 0.6990000000000001, "CR": 507, "Writing": 478, "NumTested": 58, "Math": 521, "M+CR+W": 1506, "M+CR": 1028}, "900311": {"PerTested": 0.828, "CR": 508, "Writing": 506, "NumTested": 140, "Math": 528, "M+CR+W": 1542, "M+CR": 1036}, "740388": {"PerTested": 0.71, "CR": 463, "Writing": 437, "NumTested": 186, "Math": 488, "M+CR+W": 1388, "M+CR": 951}, "90330": {"PerTested": 0.53, "CR": 399, "Writing": 397, "NumTested": 71, "Math": 449, "M+CR+W": 1245, "M+CR": 848}, "660700": {"PerTested": 0.9840000000000001, "CR": 373, "Writing": 360, "NumTested": 61, "Math": 396, "M+CR+W": 1129, "M+CR": 769}, "490362": {"PerTested": 0.537, "CR": 459, "Writing": 434, "NumTested": 109, "Math": 485, "M+CR+W": 1378, "M+CR": 944}, "260318": {"PerTested": 0.624, "CR": 502, "Writing": 476, "NumTested": 241, "Math": 517, "M+CR+W": 1495, "M+CR": 1019}, "780325": {"PerTested": 0.479, "CR": 408, "Writing": 401, "NumTested": 57, "Math": 435, "M+CR+W": 1244, "M+CR": 843}, "480480": {"PerTested": 0.5329999999999999, "CR": 453, "Writing": 425, "NumTested": 24, "Math": 458, "M+CR+W": 1336, "M+CR": 911}, "260322": {"PerTested": 0.53, "CR": 426, "Writing": 395, "NumTested": 134, "Math": 441, "M+CR+W": 1262, "M+CR": 867}, "260325": {"PerTested": 0.55, "CR": 480, "Writing": 456, "NumTested": 154, "Math": 498, "M+CR+W": 1434, "M+CR": 978}, "681681": {"PerTested": 0.8590000000000001, "CR": 586, "Writing": 568, "NumTested": 714, "Math": 596, "M+CR+W": 1750, "M+CR": 1182}, "960380": {"PerTested": 0.431, "CR": 449, "Writing": 425, "NumTested": 87, "Math": 465, "M+CR+W": 1339, "M+CR": 914}, "830700": {"PerTested": 0.773, "CR": 416, "Writing": 421, "NumTested": 58, "Math": 445, "M+CR+W": 1282, "M+CR": 861}, "600302": {"PerTested": 0.9, "CR": 539, "Writing": 534, "NumTested": 404, "Math": 564, "M+CR+W": 1637, "M+CR": 1103}, "730352": {"PerTested": 0.551, "CR": 463, "Writing": 437, "NumTested": 166, "Math": 476, "M+CR+W": 1376, "M+CR": 939}, "830705": {"PerTested": 0.613, "CR": 455, "Writing": 431, "NumTested": 38, "Math": 504, "M+CR+W": 1390, "M+CR": 959}, "390390": {"PerTested": 0.58, "CR": 458, "Writing": 446, "NumTested": 300, "Math": 478, "M+CR+W": 1382, "M+CR": 936}, "900344": {"PerTested": 0.586, "CR": 487, "Writing": 485, "NumTested": 116, "Math": 505, "M+CR+W": 1477, "M+CR": 992}, "920466": {"PerTested": 0.642, "CR": 463, "Writing": 437, "NumTested": 221, "Math": 468, "M+CR+W": 1368, "M+CR": 931}, "900348": {"PerTested": 0.653, "CR": 483, "Writing": 455, "NumTested": 143, "Math": 518, "M+CR+W": 1456, "M+CR": 1001}, "990332": {"PerTested": 0.455, "CR": 493, "Writing": 469, "NumTested": 15, "Math": 499, "M+CR+W": 1461, "M+CR": 992}, "90368": {"PerTested": 0.46, "CR": 423, "Writing": 400, "NumTested": 75, "Math": 458, "M+CR+W": 1281, "M+CR": 881}, "260354": {"PerTested": 0.938, "CR": 480, "Writing": 442, "NumTested": 45, "Math": 478, "M+CR+W": 1400, "M+CR": 958}, "130307": {"PerTested": 0.81, "CR": 495, "Writing": 481, "NumTested": 158, "Math": 524, "M+CR+W": 1500, "M+CR": 1019}, "260357": {"PerTested": 0.52, "CR": 474, "Writing": 437, "NumTested": 143, "Math": 473, "M+CR+W": 1384, "M+CR": 947}, "130310": {"PerTested": 0.562, "CR": 474, "Writing": 460, "NumTested": 141, "Math": 503, "M+CR+W": 1437, "M+CR": 977}, "260359": {"PerTested": 0.532, "CR": 422, "Writing": 409, "NumTested": 109, "Math": 445, "M+CR+W": 1276, "M+CR": 867}, "900360": {"PerTested": 0.563, "CR": 500, "Writing": 497, "NumTested": 166, "Math": 523, "M+CR+W": 1520, "M+CR": 1023}, "390700": {"PerTested": 0.889, "CR": 457, "Writing": 455, "NumTested": 48, "Math": 488, "M+CR+W": 1400, "M+CR": 945}, "430346": {"PerTested": 0.564, "CR": 476, "Writing": 452, "NumTested": 154, "Math": 484, "M+CR+W": 1412, "M+CR": 960}, "300300": {"PerTested": 0.532, "CR": 508, "Writing": 481, "NumTested": 199, "Math": 523, "M+CR+W": 1512, "M+CR": 1031}, "960386": {"PerTested": 0.465, "CR": 463, "Writing": 441, "NumTested": 47, "Math": 495, "M+CR+W": 1399, "M+CR": 958}, "600334": {"PerTested": 1.0, "CR": 504, "Writing": 486, "NumTested": 58, "Math": 525, "M+CR+W": 1515, "M+CR": 1029}, "900367": {"PerTested": 0.732, "CR": 528, "Writing": 515, "NumTested": 52, "Math": 549, "M+CR+W": 1592, "M+CR": 1077}, "130324": {"PerTested": 0.586, "CR": 496, "Writing": 478, "NumTested": 109, "Math": 517, "M+CR+W": 1491, "M+CR": 1013}, "130326": {"PerTested": 0.6709999999999999, "CR": 498, "Writing": 477, "NumTested": 143, "Math": 520, "M+CR+W": 1495, "M+CR": 1018}, "300312": {"PerTested": 0.506, "CR": 508, "Writing": 478, "NumTested": 170, "Math": 523, "M+CR+W": 1509, "M+CR": 1031}, "900377": {"PerTested": 0.847, "CR": 545, "Writing": 523, "NumTested": 216, "Math": 549, "M+CR+W": 1617, "M+CR": 1094}, "300314": {"PerTested": 0.763, "CR": 508, "Writing": 497, "NumTested": 29, "Math": 523, "M+CR+W": 1528, "M+CR": 1031}, "130332": {"PerTested": 0.784, "CR": 492, "Writing": 490, "NumTested": 250, "Math": 524, "M+CR+W": 1506, "M+CR": 1016}, "130333": {"PerTested": 0.342, "CR": 508, "Writing": 428, "NumTested": 13, "Math": 472, "M+CR+W": 1408, "M+CR": 980}, "930352": {"PerTested": 0.6, "CR": 379, "Writing": 376, "NumTested": 60, "Math": 402, "M+CR+W": 1157, "M+CR": 781}, "210210": {"PerTested": 0.664, "CR": 439, "Writing": 429, "NumTested": 89, "Math": 457, "M+CR+W": 1325, "M+CR": 896}, "430371": {"PerTested": 0.508, "CR": 462, "Writing": 442, "NumTested": 152, "Math": 455, "M+CR+W": 1359, "M+CR": 917}, "260388": {"PerTested": 0.775, "CR": 507, "Writing": 460, "NumTested": 69, "Math": 471, "M+CR+W": 1438, "M+CR": 978}, "470312": {"PerTested": 0.426, "CR": 431, "Writing": 415, "NumTested": 152, "Math": 440, "M+CR+W": 1286, "M+CR": 871}, "600361": {"PerTested": 0.6829999999999999, "CR": 507, "Writing": 492, "NumTested": 386, "Math": 528, "M+CR+W": 1527, "M+CR": 1035}, "430378": {"PerTested": 0.583, "CR": 447, "Writing": 433, "NumTested": 162, "Math": 474, "M+CR+W": 1354, "M+CR": 921}, "600364": {"PerTested": 1.0, "CR": 439, "Writing": 416, "NumTested": 14, "Math": 450, "M+CR+W": 1305, "M+CR": 889}, "770349": {"PerTested": 0.16699999999999998, "CR": 518, "Writing": 470, "NumTested": 5, "Math": 558, "M+CR+W": 1546, "M+CR": 1076}, "430384": {"PerTested": 0.513, "CR": 461, "Writing": 433, "NumTested": 115, "Math": 477, "M+CR+W": 1371, "M+CR": 938}, "800361": {"PerTested": 0.517, "CR": 466, "Writing": 445, "NumTested": 139, "Math": 483, "M+CR+W": 1394, "M+CR": 949}, "610610": {"PerTested": 0.622, "CR": 494, "Writing": 447, "NumTested": 79, "Math": 485, "M+CR+W": 1426, "M+CR": 979}, "770348": {"PerTested": 0.37799999999999995, "CR": 434, "Writing": 419, "NumTested": 157, "Math": 449, "M+CR+W": 1302, "M+CR": 883}, "120120": {"PerTested": 0.47100000000000003, "CR": 476, "Writing": 456, "NumTested": 412, "Math": 514, "M+CR+W": 1446, "M+CR": 990}, "600377": {"PerTested": 0.688, "CR": 492, "Writing": 476, "NumTested": 254, "Math": 507, "M+CR+W": 1475, "M+CR": 999}, "260411": {"PerTested": 0.875, "CR": 497, "Writing": 469, "NumTested": 56, "Math": 480, "M+CR+W": 1446, "M+CR": 977}, "980336": {"PerTested": 0.557, "CR": 474, "Writing": 461, "NumTested": 156, "Math": 502, "M+CR+W": 1437, "M+CR": 976}, "600386": {"PerTested": 0.306, "CR": 381, "Writing": 360, "NumTested": 22, "Math": 353, "M+CR+W": 1094, "M+CR": 734}, "780342": {"PerTested": 0.426, "CR": 437, "Writing": 423, "NumTested": 195, "Math": 454, "M+CR+W": 1314, "M+CR": 891}, "260424": {"PerTested": 0.446, "CR": 439, "Writing": 423, "NumTested": 141, "Math": 438, "M+CR+W": 1300, "M+CR": 877}, "410508": {"PerTested": 0.672, "CR": 515, "Writing": 497, "NumTested": 268, "Math": 515, "M+CR+W": 1527, "M+CR": 1030}, "940940": {"PerTested": 0.514, "CR": 405, "Writing": 398, "NumTested": 71, "Math": 424, "M+CR+W": 1227, "M+CR": 829}, "260427": {"PerTested": 0.509, "CR": 469, "Writing": 444, "NumTested": 172, "Math": 470, "M+CR+W": 1383, "M+CR": 939}, "170316": {"PerTested": 0.565, "CR": 437, "Writing": 424, "NumTested": 91, "Math": 452, "M+CR+W": 1313, "M+CR": 889}, "830702": {"PerTested": 0.623, "CR": 437, "Writing": 413, "NumTested": 43, "Math": 444, "M+CR+W": 1294, "M+CR": 881}, "810324": {"PerTested": 0.429, "CR": 451, "Writing": 435, "NumTested": 67, "Math": 471, "M+CR+W": 1357, "M+CR": 922}, "600405": {"PerTested": 0.8270000000000001, "CR": 461, "Writing": 442, "NumTested": 177, "Math": 477, "M+CR+W": 1380, "M+CR": 938}, "980342": {"PerTested": 0.614, "CR": 474, "Writing": 449, "NumTested": 156, "Math": 487, "M+CR+W": 1410, "M+CR": 961}, "920920": {"PerTested": 0.759, "CR": 521, "Writing": 503, "NumTested": 6577, "Math": 544, "M+CR+W": 1568, "M+CR": 1065}, "681305": {"PerTested": 0.774, "CR": 585, "Writing": 572, "NumTested": 154, "Math": 576, "M+CR+W": 1733, "M+CR": 1161}, "640346": {"PerTested": 0.502, "CR": 447, "Writing": 418, "NumTested": 126, "Math": 470, "M+CR+W": 1335, "M+CR": 917}, "640347": {"PerTested": 0.8140000000000001, "CR": 470, "Writing": 446, "NumTested": 48, "Math": 466, "M+CR+W": 1382, "M+CR": 936}, "681308": {"PerTested": 0.887, "CR": 580, "Writing": 560, "NumTested": 251, "Math": 597, "M+CR+W": 1737, "M+CR": 1177}, "430430": {"PerTested": 0.5379999999999999, "CR": 461, "Writing": 440, "NumTested": 584, "Math": 472, "M+CR+W": 1373, "M+CR": 933}, "600415": {"PerTested": 0.682, "CR": 490, "Writing": 473, "NumTested": 360, "Math": 499, "M+CR+W": 1462, "M+CR": 989}, "8080": {"PerTested": 0.674, "CR": 387, "Writing": 364, "NumTested": 118, "Math": 410, "M+CR+W": 1161, "M+CR": 797}, "681314": {"PerTested": 0.9129999999999999, "CR": 593, "Writing": 574, "NumTested": 306, "Math": 607, "M+CR+W": 1774, "M+CR": 1200}, "810340": {"PerTested": 0.75, "CR": 443, "Writing": 434, "NumTested": 102, "Math": 460, "M+CR+W": 1337, "M+CR": 903}, "260455": {"PerTested": 0.556, "CR": 415, "Writing": 404, "NumTested": 130, "Math": 421, "M+CR+W": 1240, "M+CR": 836}, "480316": {"PerTested": 0.778, "CR": 540, "Writing": 503, "NumTested": 7, "Math": 529, "M+CR+W": 1572, "M+CR": 1069}, "600426": {"PerTested": 0.51, "CR": 445, "Writing": 436, "NumTested": 251, "Math": 456, "M+CR+W": 1337, "M+CR": 901}, "640364": {"PerTested": 0.4, "CR": 464, "Writing": 442, "NumTested": 104, "Math": 499, "M+CR+W": 1405, "M+CR": 963}, "450450": {"PerTested": 0.552, "CR": 518, "Writing": 492, "NumTested": 451, "Math": 522, "M+CR+W": 1532, "M+CR": 1040}, "400308": {"PerTested": 0.402, "CR": 413, "Writing": 385, "NumTested": 68, "Math": 435, "M+CR+W": 1233, "M+CR": 848}, "290365": {"PerTested": 0.259, "CR": 462, "Writing": 456, "NumTested": 22, "Math": 476, "M+CR+W": 1394, "M+CR": 938}, "40304": {"PerTested": 0.614, "CR": 487, "Writing": 467, "NumTested": 43, "Math": 497, "M+CR+W": 1451, "M+CR": 984}, "40306": {"PerTested": 0.45, "CR": 391, "Writing": 374, "NumTested": 76, "Math": 389, "M+CR+W": 1154, "M+CR": 780}, "340340": {"PerTested": 0.6609999999999999, "CR": 493, "Writing": 472, "NumTested": 2209, "Math": 506, "M+CR+W": 1471, "M+CR": 999}, "250340": {"PerTested": 0.44, "CR": 496, "Writing": 454, "NumTested": 109, "Math": 513, "M+CR+W": 1463, "M+CR": 1009}, "680332": {"PerTested": 0.675, "CR": 511, "Writing": 480, "NumTested": 154, "Math": 513, "M+CR+W": 1504, "M+CR": 1024}, "600445": {"PerTested": 0.81, "CR": 484, "Writing": 475, "NumTested": 367, "Math": 488, "M+CR+W": 1447, "M+CR": 972}, "740740": {"PerTested": 0.623, "CR": 484, "Writing": 460, "NumTested": 806, "Math": 506, "M+CR+W": 1450, "M+CR": 990}, "210312": {"PerTested": 0.664, "CR": 439, "Writing": 429, "NumTested": 89, "Math": 457, "M+CR+W": 1325, "M+CR": 896}, "250250": {"PerTested": 0.428, "CR": 489, "Writing": 452, "NumTested": 436, "Math": 507, "M+CR+W": 1448, "M+CR": 996}, "340364": {"PerTested": 0.6759999999999999, "CR": 489, "Writing": 458, "NumTested": 300, "Math": 500, "M+CR+W": 1447, "M+CR": 989}, "920428": {"PerTested": 0.614, "CR": 509, "Writing": 487, "NumTested": 234, "Math": 538, "M+CR+W": 1534, "M+CR": 1047}, "810384": {"PerTested": 0.478, "CR": 489, "Writing": 472, "NumTested": 88, "Math": 496, "M+CR+W": 1457, "M+CR": 985}, "810385": {"PerTested": 0.75, "CR": 527, "Writing": 508, "NumTested": 27, "Math": 535, "M+CR+W": 1570, "M+CR": 1062}, "600466": {"PerTested": 0.879, "CR": 561, "Writing": 540, "NumTested": 507, "Math": 571, "M+CR+W": 1672, "M+CR": 1132}, "380308": {"PerTested": 0.551, "CR": 476, "Writing": 470, "NumTested": 43, "Math": 511, "M+CR+W": 1457, "M+CR": 987}, "510357": {"PerTested": 0.35100000000000003, "CR": 548, "Writing": 508, "NumTested": 20, "Math": 536, "M+CR+W": 1592, "M+CR": 1084}, "760388": {"PerTested": 0.462, "CR": 472, "Writing": 457, "NumTested": 73, "Math": 505, "M+CR+W": 1434, "M+CR": 977}, "650650": {"PerTested": 0.6579999999999999, "CR": 506, "Writing": 483, "NumTested": 1013, "Math": 524, "M+CR+W": 1513, "M+CR": 1030}, "850332": {"PerTested": 0.505, "CR": 475, "Writing": 441, "NumTested": 48, "Math": 493, "M+CR+W": 1409, "M+CR": 968}, "340382": {"PerTested": 0.5660000000000001, "CR": 474, "Writing": 453, "NumTested": 167, "Math": 481, "M+CR+W": 1408, "M+CR": 955}, "160160": {"PerTested": 0.608, "CR": 519, "Writing": 489, "NumTested": 322, "Math": 527, "M+CR+W": 1535, "M+CR": 1046}, "830704": {"PerTested": 0.667, "CR": 408, "Writing": 402, "NumTested": 50, "Math": 443, "M+CR+W": 1253, "M+CR": 851}, "600482": {"PerTested": 0.841, "CR": 517, "Writing": 493, "NumTested": 116, "Math": 477, "M+CR+W": 1487, "M+CR": 994}, "790378": {"PerTested": 0.5760000000000001, "CR": 489, "Writing": 472, "NumTested": 125, "Math": 508, "M+CR+W": 1469, "M+CR": 997}, "920348": {"PerTested": 0.835, "CR": 538, "Writing": 521, "NumTested": 401, "Math": 547, "M+CR+W": 1606, "M+CR": 1085}, "510376": {"PerTested": 0.406, "CR": 511, "Writing": 481, "NumTested": 43, "Math": 530, "M+CR+W": 1522, "M+CR": 1041}, "470443": {"PerTested": 0.44799999999999995, "CR": 492, "Writing": 476, "NumTested": 30, "Math": 509, "M+CR+W": 1477, "M+CR": 1001}, "182700": {"PerTested": 1.0, "CR": 510, "Writing": 480, "NumTested": 15, "Math": 477, "M+CR+W": 1467, "M+CR": 987}, "550320": {"PerTested": 0.564, "CR": 481, "Writing": 457, "NumTested": 102, "Math": 520, "M+CR+W": 1458, "M+CR": 1001}, "600498": {"PerTested": 0.235, "CR": 583, "Writing": 553, "NumTested": 12, "Math": 528, "M+CR+W": 1664, "M+CR": 1111}, "240371": {"PerTested": 0.402, "CR": 446, "Writing": 447, "NumTested": 47, "Math": 476, "M+CR+W": 1369, "M+CR": 922}, "850358": {"PerTested": 0.478, "CR": 482, "Writing": 459, "NumTested": 100, "Math": 501, "M+CR+W": 1442, "M+CR": 983}, "80312": {"PerTested": 0.6609999999999999, "CR": 373, "Writing": 353, "NumTested": 76, "Math": 388, "M+CR+W": 1114, "M+CR": 761}, "700319": {"PerTested": 0.506, "CR": 454, "Writing": 428, "NumTested": 91, "Math": 466, "M+CR+W": 1348, "M+CR": 920}, "550332": {"PerTested": 0.474, "CR": 475, "Writing": 450, "NumTested": 93, "Math": 489, "M+CR+W": 1414, "M+CR": 964}, "510399": {"PerTested": 0.441, "CR": 475, "Writing": 452, "NumTested": 137, "Math": 483, "M+CR+W": 1410, "M+CR": 958}, "890304": {"PerTested": 0.455, "CR": 423, "Writing": 396, "NumTested": 15, "Math": 443, "M+CR+W": 1262, "M+CR": 866}, "510368": {"PerTested": 0.42200000000000004, "CR": 464, "Writing": 458, "NumTested": 65, "Math": 522, "M+CR+W": 1444, "M+CR": 986}, "510402": {"PerTested": 0.303, "CR": 495, "Writing": 473, "NumTested": 73, "Math": 528, "M+CR+W": 1496, "M+CR": 1023}, "421316": {"PerTested": 0.613, "CR": 465, "Writing": 450, "NumTested": 119, "Math": 464, "M+CR+W": 1379, "M+CR": 929}, "900342": {"PerTested": 0.701, "CR": 497, "Writing": 484, "NumTested": 223, "Math": 517, "M+CR+W": 1498, "M+CR": 1014}, "470470": {"PerTested": 0.41600000000000004, "CR": 441, "Writing": 425, "NumTested": 182, "Math": 451, "M+CR+W": 1317, "M+CR": 892}, "761761": {"PerTested": 0.7879999999999999, "CR": 461, "Writing": 444, "NumTested": 190, "Math": 479, "M+CR+W": 1384, "M+CR": 940}, "550344": {"PerTested": 0.7170000000000001, "CR": 492, "Writing": 478, "NumTested": 152, "Math": 532, "M+CR+W": 1502, "M+CR": 1024}, "250314": {"PerTested": 0.273, "CR": 494, "Writing": 442, "NumTested": 21, "Math": 499, "M+CR+W": 1435, "M+CR": 993}, "840356": {"PerTested": 0.42700000000000005, "CR": 494, "Writing": 446, "NumTested": 35, "Math": 538, "M+CR+W": 1478, "M+CR": 1032}, "870870": {"PerTested": 0.40399999999999997, "CR": 487, "Writing": 461, "NumTested": 46, "Math": 473, "M+CR+W": 1421, "M+CR": 960}, "600535": {"PerTested": 0.762, "CR": 513, "Writing": 496, "NumTested": 298, "Math": 525, "M+CR+W": 1534, "M+CR": 1038}, "761304": {"PerTested": 0.7879999999999999, "CR": 461, "Writing": 444, "NumTested": 190, "Math": 479, "M+CR+W": 1384, "M+CR": 940}, "291291": {"PerTested": 0.55, "CR": 445, "Writing": 421, "NumTested": 83, "Math": 454, "M+CR+W": 1320, "M+CR": 899}, "380380": {"PerTested": 0.551, "CR": 476, "Writing": 470, "NumTested": 43, "Math": 511, "M+CR+W": 1457, "M+CR": 987}, "340446": {"PerTested": 0.102, "CR": 485, "Writing": 467, "NumTested": 6, "Math": 450, "M+CR+W": 1402, "M+CR": 935}, "600376": {"PerTested": 0.39399999999999996, "CR": 424, "Writing": 403, "NumTested": 61, "Math": 435, "M+CR+W": 1262, "M+CR": 859}, "550368": {"PerTested": 0.586, "CR": 458, "Writing": 428, "NumTested": 102, "Math": 498, "M+CR+W": 1384, "M+CR": 956}, "292324": {"PerTested": 0.748, "CR": 425, "Writing": 405, "NumTested": 95, "Math": 441, "M+CR+W": 1271, "M+CR": 866}, "920316": {"PerTested": 0.8859999999999999, "CR": 539, "Writing": 519, "NumTested": 468, "Math": 587, "M+CR+W": 1645, "M+CR": 1126}, "340454": {"PerTested": 0.836, "CR": 526, "Writing": 506, "NumTested": 326, "Math": 544, "M+CR+W": 1576, "M+CR": 1070}, "280316": {"PerTested": 0.768, "CR": 477, "Writing": 443, "NumTested": 73, "Math": 513, "M+CR+W": 1433, "M+CR": 990}, "640350": {"PerTested": 0.5589999999999999, "CR": 468, "Writing": 442, "NumTested": 165, "Math": 487, "M+CR+W": 1397, "M+CR": 955}, "340460": {"PerTested": 0.527, "CR": 448, "Writing": 423, "NumTested": 129, "Math": 445, "M+CR+W": 1316, "M+CR": 893}, "111700": {"PerTested": 0.3, "CR": 578, "Writing": 527, "NumTested": 9, "Math": 539, "M+CR+W": 1644, "M+CR": 1117}, "220220": {"PerTested": 0.596, "CR": 494, "Writing": 492, "NumTested": 53, "Math": 524, "M+CR+W": 1510, "M+CR": 1018}, "710342": {"PerTested": 0.632, "CR": 511, "Writing": 485, "NumTested": 153, "Math": 519, "M+CR+W": 1515, "M+CR": 1030}, "360360": {"PerTested": 0.425, "CR": 466, "Writing": 451, "NumTested": 54, "Math": 474, "M+CR+W": 1391, "M+CR": 940}, "290290": {"PerTested": 0.534, "CR": 488, "Writing": 463, "NumTested": 668, "Math": 510, "M+CR+W": 1461, "M+CR": 998}, "250356": {"PerTested": 0.531, "CR": 485, "Writing": 456, "NumTested": 233, "Math": 504, "M+CR+W": 1445, "M+CR": 989}, "920318": {"PerTested": 0.7609999999999999, "CR": 534, "Writing": 521, "NumTested": 315, "Math": 568, "M+CR+W": 1623, "M+CR": 1102}, "120310": {"PerTested": 0.604, "CR": 480, "Writing": 456, "NumTested": 32, "Math": 503, "M+CR+W": 1439, "M+CR": 983}, "110323": {"PerTested": 0.11599999999999999, "CR": 592, "Writing": 514, "NumTested": 5, "Math": 524, "M+CR+W": 1630, "M+CR": 1116}, "590328": {"PerTested": 0.532, "CR": 488, "Writing": 462, "NumTested": 25, "Math": 482, "M+CR+W": 1432, "M+CR": 970}, "180308": {"PerTested": 0.611, "CR": 500, "Writing": 466, "NumTested": 107, "Math": 526, "M+CR+W": 1492, "M+CR": 1026}, "420346": {"PerTested": 0.435, "CR": 393, "Writing": 394, "NumTested": 73, "Math": 416, "M+CR+W": 1203, "M+CR": 809}, "120318": {"PerTested": 0.488, "CR": 473, "Writing": 452, "NumTested": 123, "Math": 502, "M+CR+W": 1427, "M+CR": 975}, "520520": {"PerTested": 0.648, "CR": 439, "Writing": 420, "NumTested": 59, "Math": 467, "M+CR+W": 1326, "M+CR": 906}, "120314": {"PerTested": 0.39899999999999997, "CR": 486, "Writing": 468, "NumTested": 81, "Math": 543, "M+CR+W": 1497, "M+CR": 1029}, "690690": {"PerTested": 0.43200000000000005, "CR": 494, "Writing": 454, "NumTested": 41, "Math": 526, "M+CR+W": 1474, "M+CR": 1020}, "600579": {"PerTested": 0.53, "CR": 425, "Writing": 408, "NumTested": 176, "Math": 437, "M+CR+W": 1270, "M+CR": 862}, "250372": {"PerTested": 0.28600000000000003, "CR": 487, "Writing": 439, "NumTested": 73, "Math": 508, "M+CR+W": 1434, "M+CR": 995}, "340486": {"PerTested": 0.6409999999999999, "CR": 432, "Writing": 409, "NumTested": 173, "Math": 443, "M+CR+W": 1284, "M+CR": 875}, "111111": {"PerTested": 0.7, "CR": 535, "Writing": 509, "NumTested": 173, "Math": 528, "M+CR+W": 1572, "M+CR": 1063}, "200200": {"PerTested": 0.573, "CR": 484, "Writing": 463, "NumTested": 137, "Math": 484, "M+CR+W": 1431, "M+CR": 968}, "980318": {"PerTested": 0.429, "CR": 445, "Writing": 429, "NumTested": 84, "Math": 487, "M+CR+W": 1361, "M+CR": 932}, "290315": {"PerTested": 0.9259999999999999, "CR": 560, "Writing": 521, "NumTested": 25, "Math": 562, "M+CR+W": 1643, "M+CR": 1122}, "900336": {"PerTested": 0.5579999999999999, "CR": 393, "Writing": 378, "NumTested": 77, "Math": 404, "M+CR+W": 1175, "M+CR": 797}, "340495": {"PerTested": 0.838, "CR": 526, "Writing": 505, "NumTested": 331, "Math": 548, "M+CR+W": 1579, "M+CR": 1074}, "340496": {"PerTested": 0.6709999999999999, "CR": 518, "Writing": 504, "NumTested": 247, "Math": 526, "M+CR+W": 1548, "M+CR": 1044}, "330328": {"PerTested": 0.373, "CR": 384, "Writing": 374, "NumTested": 28, "Math": 440, "M+CR+W": 1198, "M+CR": 824}, "600480": {"PerTested": 0.8190000000000001, "CR": 524, "Writing": 512, "NumTested": 390, "Math": 537, "M+CR+W": 1573, "M+CR": 1061}, "290324": {"PerTested": 0.5429999999999999, "CR": 468, "Writing": 458, "NumTested": 108, "Math": 500, "M+CR+W": 1426, "M+CR": 968}, "422422": {"PerTested": 0.8170000000000001, "CR": 341, "Writing": 338, "NumTested": 58, "Math": 392, "M+CR+W": 1071, "M+CR": 733}, "600600": {"PerTested": 0.685, "CR": 495, "Writing": 480, "NumTested": 5240, "Math": 507, "M+CR+W": 1482, "M+CR": 1002}, "100100": {"PerTested": 0.414, "CR": 475, "Writing": 460, "NumTested": 326, "Math": 489, "M+CR+W": 1424, "M+CR": 964}, "120346": {"PerTested": 0.512, "CR": 471, "Writing": 447, "NumTested": 64, "Math": 522, "M+CR+W": 1440, "M+CR": 993}, "760348": {"PerTested": 0.494, "CR": 487, "Writing": 463, "NumTested": 82, "Math": 497, "M+CR+W": 1447, "M+CR": 984}, "110110": {"PerTested": 0.597, "CR": 519, "Writing": 492, "NumTested": 966, "Math": 536, "M+CR+W": 1547, "M+CR": 1055}, "750318": {"PerTested": 0.615, "CR": 491, "Writing": 461, "NumTested": 96, "Math": 513, "M+CR+W": 1465, "M+CR": 1004}, "290336": {"PerTested": 0.5820000000000001, "CR": 501, "Writing": 481, "NumTested": 135, "Math": 512, "M+CR+W": 1494, "M+CR": 1013}, "560560": {"PerTested": 0.5720000000000001, "CR": 494, "Writing": 464, "NumTested": 151, "Math": 505, "M+CR+W": 1463, "M+CR": 999}, "760354": {"PerTested": 0.635, "CR": 504, "Writing": 487, "NumTested": 54, "Math": 516, "M+CR+W": 1507, "M+CR": 1020}, "790790": {"PerTested": 0.552, "CR": 471, "Writing": 456, "NumTested": 431, "Math": 487, "M+CR+W": 1414, "M+CR": 958}, "760358": {"PerTested": 0.415, "CR": 487, "Writing": 461, "NumTested": 97, "Math": 509, "M+CR+W": 1457, "M+CR": 996}, "290348": {"PerTested": 0.648, "CR": 495, "Writing": 460, "NumTested": 206, "Math": 521, "M+CR+W": 1476, "M+CR": 1016}, "421421": {"PerTested": 0.613, "CR": 465, "Writing": 450, "NumTested": 119, "Math": 464, "M+CR+W": 1379, "M+CR": 929}, "510510": {"PerTested": 0.498, "CR": 492, "Writing": 470, "NumTested": 867, "Math": 517, "M+CR+W": 1479, "M+CR": 1009}, "390704": {"PerTested": 0.586, "CR": 469, "Writing": 464, "NumTested": 51, "Math": 489, "M+CR+W": 1422, "M+CR": 958}, "390705": {"PerTested": 0.667, "CR": 451, "Writing": 438, "NumTested": 70, "Math": 469, "M+CR+W": 1358, "M+CR": 920}, "120370": {"PerTested": 0.544, "CR": 474, "Writing": 456, "NumTested": 112, "Math": 506, "M+CR+W": 1436, "M+CR": 980}, "160313": {"PerTested": 0.419, "CR": 509, "Writing": 476, "NumTested": 49, "Math": 502, "M+CR+W": 1487, "M+CR": 1011}, "160314": {"PerTested": 0.8190000000000001, "CR": 527, "Writing": 503, "NumTested": 136, "Math": 531, "M+CR+W": 1561, "M+CR": 1058}, "630332": {"PerTested": 0.496, "CR": 455, "Writing": 429, "NumTested": 58, "Math": 490, "M+CR+W": 1374, "M+CR": 945}, "130314": {"PerTested": 0.527, "CR": 502, "Writing": 480, "NumTested": 136, "Math": 516, "M+CR+W": 1498, "M+CR": 1018}, "910910": {"PerTested": 0.465, "CR": 418, "Writing": 405, "NumTested": 200, "Math": 448, "M+CR+W": 1271, "M+CR": 866}, "630336": {"PerTested": 0.682, "CR": 518, "Writing": 497, "NumTested": 294, "Math": 530, "M+CR+W": 1545, "M+CR": 1048}, "420420": {"PerTested": 0.44299999999999995, "CR": 390, "Writing": 386, "NumTested": 124, "Math": 399, "M+CR+W": 1175, "M+CR": 789}, "990322": {"PerTested": 0.528, "CR": 481, "Writing": 461, "NumTested": 105, "Math": 516, "M+CR+W": 1458, "M+CR": 997}, "780385": {"PerTested": 0.391, "CR": 471, "Writing": 449, "NumTested": 25, "Math": 495, "M+CR+W": 1415, "M+CR": 966}, "130316": {"PerTested": 0.6679999999999999, "CR": 516, "Writing": 501, "NumTested": 219, "Math": 541, "M+CR+W": 1558, "M+CR": 1057}, "340556": {"PerTested": 0.706, "CR": 528, "Writing": 507, "NumTested": 314, "Math": 542, "M+CR+W": 1577, "M+CR": 1070}, "140386": {"PerTested": 0.508, "CR": 487, "Writing": 467, "NumTested": 167, "Math": 528, "M+CR+W": 1482, "M+CR": 1015}, "500302": {"PerTested": 0.375, "CR": 435, "Writing": 435, "NumTested": 6, "Math": 480, "M+CR+W": 1350, "M+CR": 915}, "970320": {"PerTested": 0.495, "CR": 507, "Writing": 486, "NumTested": 49, "Math": 512, "M+CR+W": 1505, "M+CR": 1019}, "290388": {"PerTested": 0.473, "CR": 476, "Writing": 452, "NumTested": 69, "Math": 505, "M+CR+W": 1433, "M+CR": 981}, "900366": {"PerTested": 0.721, "CR": 513, "Writing": 495, "NumTested": 129, "Math": 536, "M+CR+W": 1544, "M+CR": 1049}, "330326": {"PerTested": 0.64, "CR": 480, "Writing": 475, "NumTested": 32, "Math": 515, "M+CR+W": 1470, "M+CR": 995}, "160344": {"PerTested": 0.555, "CR": 515, "Writing": 480, "NumTested": 137, "Math": 533, "M+CR+W": 1528, "M+CR": 1048}, "241241": {"PerTested": 0.6, "CR": 444, "Writing": 439, "NumTested": 78, "Math": 468, "M+CR+W": 1351, "M+CR": 912}, "330330": {"PerTested": 0.451, "CR": 437, "Writing": 420, "NumTested": 213, "Math": 468, "M+CR+W": 1325, "M+CR": 905}, "260700": {"PerTested": 0.9209999999999999, "CR": 454, "Writing": 442, "NumTested": 35, "Math": 460, "M+CR+W": 1356, "M+CR": 914}, "30304": {"PerTested": 0.511, "CR": 481, "Writing": 450, "NumTested": 48, "Math": 490, "M+CR+W": 1421, "M+CR": 971}, "110352": {"PerTested": 0.604, "CR": 500, "Writing": 468, "NumTested": 148, "Math": 513, "M+CR+W": 1481, "M+CR": 1013}, "650342": {"PerTested": 0.76, "CR": 527, "Writing": 504, "NumTested": 314, "Math": 555, "M+CR+W": 1586, "M+CR": 1082}, "600508": {"PerTested": 0.9590000000000001, "CR": 561, "Writing": 550, "NumTested": 443, "Math": 582, "M+CR+W": 1693, "M+CR": 1143}, "730730": {"PerTested": 0.551, "CR": 463, "Writing": 437, "NumTested": 166, "Math": 476, "M+CR+W": 1376, "M+CR": 939}, "330350": {"PerTested": 0.397, "CR": 435, "Writing": 401, "NumTested": 83, "Math": 462, "M+CR+W": 1298, "M+CR": 897}, "240240": {"PerTested": 0.45299999999999996, "CR": 440, "Writing": 427, "NumTested": 167, "Math": 467, "M+CR+W": 1334, "M+CR": 907}, "600690": {"PerTested": 0.5, "CR": 396, "Writing": 380, "NumTested": 34, "Math": 420, "M+CR+W": 1196, "M+CR": 816}, "600691": {"PerTested": 0.373, "CR": 372, "Writing": 364, "NumTested": 25, "Math": 366, "M+CR+W": 1102, "M+CR": 738}, "500340": {"PerTested": 0.578, "CR": 498, "Writing": 475, "NumTested": 89, "Math": 517, "M+CR+W": 1490, "M+CR": 1015}, "600693": {"PerTested": 0.63, "CR": 474, "Writing": 444, "NumTested": 46, "Math": 468, "M+CR+W": 1386, "M+CR": 942}, "330358": {"PerTested": 0.511, "CR": 440, "Writing": 436, "NumTested": 70, "Math": 464, "M+CR+W": 1340, "M+CR": 904}, "600695": {"PerTested": 0.63, "CR": 443, "Writing": 418, "NumTested": 51, "Math": 447, "M+CR+W": 1308, "M+CR": 890}, "600696": {"PerTested": 0.596, "CR": 410, "Writing": 408, "NumTested": 53, "Math": 431, "M+CR+W": 1249, "M+CR": 841}, "600697": {"PerTested": 0.85, "CR": 460, "Writing": 430, "NumTested": 68, "Math": 475, "M+CR+W": 1365, "M+CR": 935}, "200314": {"PerTested": 0.439, "CR": 523, "Writing": 481, "NumTested": 18, "Math": 527, "M+CR+W": 1531, "M+CR": 1050}, "600699": {"PerTested": 0.379, "CR": 408, "Writing": 412, "NumTested": 25, "Math": 437, "M+CR+W": 1257, "M+CR": 845}, "670333": {"PerTested": 0.526, "CR": 457, "Writing": 432, "NumTested": 100, "Math": 464, "M+CR+W": 1353, "M+CR": 921}, "640640": {"PerTested": 0.519, "CR": 460, "Writing": 438, "NumTested": 577, "Math": 485, "M+CR+W": 1383, "M+CR": 945}, "960960": {"PerTested": 0.48, "CR": 463, "Writing": 441, "NumTested": 567, "Math": 487, "M+CR+W": 1391, "M+CR": 950}, "670340": {"PerTested": 0.5489999999999999, "CR": 489, "Writing": 459, "NumTested": 100, "Math": 513, "M+CR+W": 1461, "M+CR": 1002}, "150150": {"PerTested": 0.6809999999999999, "CR": 480, "Writing": 451, "NumTested": 81, "Math": 479, "M+CR+W": 1410, "M+CR": 959}, "820324": {"PerTested": 0.519, "CR": 477, "Writing": 438, "NumTested": 42, "Math": 487, "M+CR+W": 1402, "M+CR": 964}, "200328": {"PerTested": 0.565, "CR": 487, "Writing": 470, "NumTested": 61, "Math": 482, "M+CR+W": 1439, "M+CR": 969}, "800396": {"PerTested": 0.635, "CR": 491, "Writing": 476, "NumTested": 120, "Math": 513, "M+CR+W": 1480, "M+CR": 1004}, "862862": {"PerTested": 0.547, "CR": 487, "Writing": 473, "NumTested": 58, "Math": 527, "M+CR+W": 1487, "M+CR": 1014}, "670352": {"PerTested": 0.5489999999999999, "CR": 504, "Writing": 475, "NumTested": 100, "Math": 530, "M+CR+W": 1509, "M+CR": 1034}, "970388": {"PerTested": 0.45, "CR": 494, "Writing": 471, "NumTested": 59, "Math": 532, "M+CR+W": 1497, "M+CR": 1026}, "840302": {"PerTested": 0.741, "CR": 425, "Writing": 409, "NumTested": 80, "Math": 448, "M+CR+W": 1282, "M+CR": 873}, "550550": {"PerTested": 0.5870000000000001, "CR": 478, "Writing": 456, "NumTested": 449, "Math": 513, "M+CR+W": 1447, "M+CR": 991}, "920552": {"PerTested": 0.7190000000000001, "CR": 516, "Writing": 495, "NumTested": 276, "Math": 535, "M+CR+W": 1546, "M+CR": 1051}, "800408": {"PerTested": 0.5670000000000001, "CR": 455, "Writing": 428, "NumTested": 135, "Math": 471, "M+CR+W": 1354, "M+CR": 926}, "292292": {"PerTested": 0.748, "CR": 425, "Writing": 405, "NumTested": 95, "Math": 441, "M+CR+W": 1271, "M+CR": 866}, "800400": {"PerTested": 0.45799999999999996, "CR": 475, "Writing": 462, "NumTested": 87, "Math": 507, "M+CR+W": 1444, "M+CR": 982}, "540315": {"PerTested": 0.503, "CR": 404, "Writing": 394, "NumTested": 98, "Math": 438, "M+CR+W": 1236, "M+CR": 842}, "670364": {"PerTested": 0.68, "CR": 478, "Writing": 459, "NumTested": 170, "Math": 505, "M+CR+W": 1442, "M+CR": 983}, "540317": {"PerTested": 0.282, "CR": 463, "Writing": 409, "NumTested": 11, "Math": 455, "M+CR+W": 1327, "M+CR": 918}, "200350": {"PerTested": 0.667, "CR": 541, "Writing": 524, "NumTested": 14, "Math": 532, "M+CR+W": 1597, "M+CR": 1073}, "670320": {"PerTested": 0.541, "CR": 480, "Writing": 459, "NumTested": 73, "Math": 483, "M+CR+W": 1422, "M+CR": 963}, "540324": {"PerTested": 0.483, "CR": 452, "Writing": 419, "NumTested": 102, "Math": 472, "M+CR+W": 1343, "M+CR": 924}, "510406": {"PerTested": 0.609, "CR": 497, "Writing": 470, "NumTested": 270, "Math": 523, "M+CR+W": 1490, "M+CR": 1020}, "950950": {"PerTested": 0.7909999999999999, "CR": 540, "Writing": 506, "NumTested": 216, "Math": 544, "M+CR+W": 1590, "M+CR": 1084}, "720316": {"PerTested": 0.54, "CR": 452, "Writing": 435, "NumTested": 68, "Math": 494, "M+CR+W": 1381, "M+CR": 946}, "700700": {"PerTested": 0.58, "CR": 456, "Writing": 432, "NumTested": 233, "Math": 464, "M+CR+W": 1352, "M+CR": 920}, "460460": {"PerTested": 0.58, "CR": 393, "Writing": 377, "NumTested": 142, "Math": 412, "M+CR+W": 1182, "M+CR": 805}, "930930": {"PerTested": 0.741, "CR": 408, "Writing": 399, "NumTested": 117, "Math": 419, "M+CR+W": 1226, "M+CR": 827}, "540336": {"PerTested": 0.366, "CR": 494, "Writing": 469, "NumTested": 59, "Math": 515, "M+CR+W": 1478, "M+CR": 1009}, "710321": {"PerTested": 0.331, "CR": 446, "Writing": 413, "NumTested": 42, "Math": 461, "M+CR+W": 1320, "M+CR": 907}, "880308": {"PerTested": 0.721, "CR": 511, "Writing": 475, "NumTested": 106, "Math": 525, "M+CR+W": 1511, "M+CR": 1036}, "710326": {"PerTested": 0.611, "CR": 437, "Writing": 418, "NumTested": 91, "Math": 459, "M+CR+W": 1314, "M+CR": 896}, "710327": {"PerTested": 0.457, "CR": 498, "Writing": 477, "NumTested": 32, "Math": 467, "M+CR+W": 1442, "M+CR": 965}, "200308": {"PerTested": 0.7290000000000001, "CR": 445, "Writing": 428, "NumTested": 43, "Math": 456, "M+CR+W": 1329, "M+CR": 901}, "70330": {"PerTested": 0.5379999999999999, "CR": 463, "Writing": 434, "NumTested": 43, "Math": 493, "M+CR+W": 1390, "M+CR": 956}, "860860": {"PerTested": 0.40299999999999997, "CR": 486, "Writing": 465, "NumTested": 224, "Math": 516, "M+CR+W": 1467, "M+CR": 1002}, "920562": {"PerTested": 0.7490000000000001, "CR": 466, "Writing": 445, "NumTested": 277, "Math": 486, "M+CR+W": 1397, "M+CR": 952}, "370370": {"PerTested": 0.449, "CR": 458, "Writing": 424, "NumTested": 57, "Math": 476, "M+CR+W": 1358, "M+CR": 934}, "70339": {"PerTested": 0.58, "CR": 438, "Writing": 417, "NumTested": 58, "Math": 478, "M+CR+W": 1333, "M+CR": 916}, "111302": {"PerTested": 0.7659999999999999, "CR": 533, "Writing": 508, "NumTested": 164, "Math": 527, "M+CR+W": 1568, "M+CR": 1060}, "880328": {"PerTested": 0.5379999999999999, "CR": 476, "Writing": 449, "NumTested": 35, "Math": 489, "M+CR+W": 1414, "M+CR": 965}, "240334": {"PerTested": 0.45299999999999996, "CR": 421, "Writing": 411, "NumTested": 48, "Math": 466, "M+CR+W": 1298, "M+CR": 887}, "410319": {"PerTested": 0.722, "CR": 406, "Writing": 402, "NumTested": 122, "Math": 422, "M+CR+W": 1230, "M+CR": 828}, "10360": {"PerTested": 0.479, "CR": 406, "Writing": 386, "NumTested": 67, "Math": 438, "M+CR+W": 1230, "M+CR": 844}, "770770": {"PerTested": 0.335, "CR": 437, "Writing": 421, "NumTested": 162, "Math": 452, "M+CR+W": 1310, "M+CR": 889}, "230350": {"PerTested": 0.441, "CR": 496, "Writing": 474, "NumTested": 127, "Math": 535, "M+CR+W": 1505, "M+CR": 1031}, "410326": {"PerTested": 0.708, "CR": 373, "Writing": 371, "NumTested": 17, "Math": 372, "M+CR+W": 1116, "M+CR": 745}, "280280": {"PerTested": 0.8029999999999999, "CR": 500, "Writing": 475, "NumTested": 269, "Math": 520, "M+CR+W": 1495, "M+CR": 1020}, "340700": {"PerTested": 0.45799999999999996, "CR": 455, "Writing": 432, "NumTested": 22, "Math": 474, "M+CR+W": 1361, "M+CR": 929}, "340701": {"PerTested": 0.7040000000000001, "CR": 411, "Writing": 379, "NumTested": 38, "Math": 408, "M+CR+W": 1198, "M+CR": 819}, "340702": {"PerTested": 0.48200000000000004, "CR": 359, "Writing": 338, "NumTested": 27, "Math": 393, "M+CR+W": 1090, "M+CR": 752}, "340703": {"PerTested": 0.47600000000000003, "CR": 399, "Writing": 377, "NumTested": 20, "Math": 406, "M+CR+W": 1182, "M+CR": 805}, "110304": {"PerTested": 0.5770000000000001, "CR": 546, "Writing": 515, "NumTested": 154, "Math": 559, "M+CR+W": 1620, "M+CR": 1105}, "240380": {"PerTested": 0.5379999999999999, "CR": 430, "Writing": 405, "NumTested": 49, "Math": 449, "M+CR+W": 1284, "M+CR": 879}, "900316": {"PerTested": 0.462, "CR": 434, "Writing": 427, "NumTested": 91, "Math": 469, "M+CR+W": 1330, "M+CR": 903}, "680680": {"PerTested": 0.74, "CR": 520, "Writing": 498, "NumTested": 313, "Math": 523, "M+CR+W": 1541, "M+CR": 1043}, "820348": {"PerTested": 0.43700000000000006, "CR": 452, "Writing": 438, "NumTested": 45, "Math": 467, "M+CR+W": 1357, "M+CR": 919}, "750317": {"PerTested": 0.6920000000000001, "CR": 448, "Writing": 433, "NumTested": 9, "Math": 449, "M+CR+W": 1330, "M+CR": 897}, "190190": {"PerTested": 0.674, "CR": 478, "Writing": 461, "NumTested": 279, "Math": 494, "M+CR+W": 1433, "M+CR": 972}, "820349": {"PerTested": 0.444, "CR": 428, "Writing": 404, "NumTested": 36, "Math": 439, "M+CR+W": 1271, "M+CR": 867}, "280304": {"PerTested": 0.643, "CR": 527, "Writing": 495, "NumTested": 27, "Math": 534, "M+CR+W": 1556, "M+CR": 1061}, "600692": {"PerTested": 0.35200000000000004, "CR": 383, "Writing": 357, "NumTested": 25, "Math": 416, "M+CR+W": 1156, "M+CR": 799}, "110322": {"PerTested": 0.424, "CR": 558, "Writing": 520, "NumTested": 25, "Math": 552, "M+CR+W": 1630, "M+CR": 1110}, "410355": {"PerTested": 0.7020000000000001, "CR": 391, "Writing": 382, "NumTested": 221, "Math": 404, "M+CR+W": 1177, "M+CR": 795}, "820352": {"PerTested": 0.496, "CR": 454, "Writing": 432, "NumTested": 59, "Math": 489, "M+CR+W": 1375, "M+CR": 943}, "240373": {"PerTested": 0.451, "CR": 491, "Writing": 470, "NumTested": 23, "Math": 490, "M+CR+W": 1451, "M+CR": 981}, "410358": {"PerTested": 0.518, "CR": 452, "Writing": 436, "NumTested": 114, "Math": 464, "M+CR+W": 1352, "M+CR": 916}, "900393": {"PerTested": 0.943, "CR": 532, "Writing": 528, "NumTested": 281, "Math": 561, "M+CR+W": 1621, "M+CR": 1093}, "580344": {"PerTested": 0.39399999999999996, "CR": 420, "Writing": 404, "NumTested": 37, "Math": 465, "M+CR+W": 1289, "M+CR": 885}, "40700": {"PerTested": 0.929, "CR": 433, "Writing": 407, "NumTested": 39, "Math": 463, "M+CR+W": 1303, "M+CR": 896}, "790314": {"PerTested": 0.5660000000000001, "CR": 475, "Writing": 461, "NumTested": 107, "Math": 487, "M+CR+W": 1423, "M+CR": 962}, "590590": {"PerTested": 0.428, "CR": 477, "Writing": 460, "NumTested": 170, "Math": 495, "M+CR+W": 1432, "M+CR": 972}, "110336": {"PerTested": 0.701, "CR": 511, "Writing": 484, "NumTested": 117, "Math": 528, "M+CR+W": 1523, "M+CR": 1039}, "520320": {"PerTested": 0.648, "CR": 439, "Writing": 420, "NumTested": 59, "Math": 467, "M+CR+W": 1326, "M+CR": 906}, "110340": {"PerTested": 0.491, "CR": 470, "Writing": 445, "NumTested": 114, "Math": 501, "M+CR+W": 1416, "M+CR": 971}, "110380": {"PerTested": 0.649, "CR": 517, "Writing": 485, "NumTested": 157, "Math": 542, "M+CR+W": 1544, "M+CR": 1059}, "280330": {"PerTested": 0.88, "CR": 506, "Writing": 486, "NumTested": 169, "Math": 520, "M+CR+W": 1512, "M+CR": 1026}, "450316": {"PerTested": 0.507, "CR": 509, "Writing": 482, "NumTested": 102, "Math": 519, "M+CR+W": 1510, "M+CR": 1028}, "990990": {"PerTested": 0.48700000000000004, "CR": 484, "Writing": 462, "NumTested": 190, "Math": 512, "M+CR+W": 1458, "M+CR": 996}, "920701": {"PerTested": 0.342, "CR": 439, "Writing": 406, "NumTested": 25, "Math": 465, "M+CR+W": 1310, "M+CR": 904}, "580368": {"PerTested": 0.525, "CR": 453, "Writing": 426, "NumTested": 64, "Math": 479, "M+CR+W": 1358, "M+CR": 932}, "500500": {"PerTested": 0.47100000000000003, "CR": 495, "Writing": 472, "NumTested": 98, "Math": 513, "M+CR+W": 1480, "M+CR": 1008}, "410390": {"PerTested": 0.903, "CR": 499, "Writing": 466, "NumTested": 56, "Math": 456, "M+CR+W": 1421, "M+CR": 955}, "410391": {"PerTested": 1.0, "CR": 556, "Writing": 527, "NumTested": 25, "Math": 548, "M+CR+W": 1631, "M+CR": 1104}, "410394": {"PerTested": 0.754, "CR": 539, "Writing": 519, "NumTested": 288, "Math": 541, "M+CR+W": 1599, "M+CR": 1080}, "410395": {"PerTested": 1.0, "CR": 638, "Writing": 622, "NumTested": 57, "Math": 660, "M+CR+W": 1920, "M+CR": 1298}, "620316": {"PerTested": 0.523, "CR": 418, "Writing": 401, "NumTested": 56, "Math": 417, "M+CR+W": 1236, "M+CR": 835}, "450334": {"PerTested": 0.7, "CR": 531, "Writing": 498, "NumTested": 119, "Math": 531, "M+CR+W": 1560, "M+CR": 1062}, "410399": {"PerTested": 0.892, "CR": 481, "Writing": 455, "NumTested": 33, "Math": 488, "M+CR+W": 1424, "M+CR": 969}, "150304": {"PerTested": 0.643, "CR": 489, "Writing": 457, "NumTested": 54, "Math": 491, "M+CR+W": 1437, "M+CR": 980}, "410401": {"PerTested": 0.542, "CR": 489, "Writing": 443, "NumTested": 26, "Math": 480, "M+CR+W": 1412, "M+CR": 969}, "900900": {"PerTested": 0.687, "CR": 503, "Writing": 491, "NumTested": 1635, "Math": 524, "M+CR+W": 1518, "M+CR": 1027}, "450341": {"PerTested": 0.519, "CR": 503, "Writing": 487, "NumTested": 95, "Math": 499, "M+CR+W": 1489, "M+CR": 1002}, "410406": {"PerTested": 0.6890000000000001, "CR": 470, "Writing": 458, "NumTested": 173, "Math": 486, "M+CR+W": 1414, "M+CR": 956}, "410407": {"PerTested": 0.5, "CR": 428, "Writing": 444, "NumTested": 8, "Math": 483, "M+CR+W": 1355, "M+CR": 911}, "410408": {"PerTested": 0.757, "CR": 471, "Writing": 434, "NumTested": 28, "Math": 461, "M+CR+W": 1366, "M+CR": 932}, "410410": {"PerTested": 0.7140000000000001, "CR": 484, "Writing": 468, "NumTested": 3402, "Math": 493, "M+CR+W": 1445, "M+CR": 977}, "422700": {"PerTested": 0.8170000000000001, "CR": 341, "Writing": 338, "NumTested": 58, "Math": 392, "M+CR+W": 1071, "M+CR": 733}, "920702": {"PerTested": 0.22, "CR": 466, "Writing": 428, "NumTested": 20, "Math": 483, "M+CR+W": 1377, "M+CR": 949}, "410589": {"PerTested": 0.92, "CR": 555, "Writing": 530, "NumTested": 46, "Math": 538, "M+CR+W": 1623, "M+CR": 1093}, "450352": {"PerTested": 0.547, "CR": 524, "Writing": 498, "NumTested": 135, "Math": 534, "M+CR+W": 1556, "M+CR": 1058}, "370312": {"PerTested": 0.449, "CR": 458, "Writing": 424, "NumTested": 57, "Math": 476, "M+CR+W": 1358, "M+CR": 934}, "620340": {"PerTested": 0.478, "CR": 419, "Writing": 434, "NumTested": 54, "Math": 477, "M+CR+W": 1330, "M+CR": 896}, "320309": {"PerTested": 1.0, "CR": 469, "Writing": 463, "NumTested": 82, "Math": 485, "M+CR+W": 1417, "M+CR": 954}, "320312": {"PerTested": 0.797, "CR": 532, "Writing": 512, "NumTested": 325, "Math": 529, "M+CR+W": 1573, "M+CR": 1061}, "810810": {"PerTested": 0.517, "CR": 467, "Writing": 452, "NumTested": 285, "Math": 481, "M+CR+W": 1400, "M+CR": 948}, "80700": {"PerTested": 0.7240000000000001, "CR": 411, "Writing": 383, "NumTested": 42, "Math": 449, "M+CR+W": 1243, "M+CR": 860}, "320317": {"PerTested": 0.8059999999999999, "CR": 426, "Writing": 395, "NumTested": 29, "Math": 410, "M+CR+W": 1231, "M+CR": 836}, "320320": {"PerTested": 0.731, "CR": 475, "Writing": 452, "NumTested": 1545, "Math": 476, "M+CR+W": 1403, "M+CR": 951}, "320322": {"PerTested": 0.375, "CR": 435, "Writing": 383, "NumTested": 12, "Math": 390, "M+CR+W": 1208, "M+CR": 825}, "320323": {"PerTested": 0.88, "CR": 538, "Writing": 523, "NumTested": 125, "Math": 534, "M+CR+W": 1595, "M+CR": 1072}, "960324": {"PerTested": 0.494, "CR": 469, "Writing": 444, "NumTested": 125, "Math": 499, "M+CR+W": 1412, "M+CR": 968}, "320325": {"PerTested": 0.679, "CR": 415, "Writing": 403, "NumTested": 167, "Math": 420, "M+CR+W": 1238, "M+CR": 835}, "630360": {"PerTested": 0.46399999999999997, "CR": 495, "Writing": 468, "NumTested": 116, "Math": 512, "M+CR+W": 1475, "M+CR": 1007}, "840332": {"PerTested": 0.542, "CR": 457, "Writing": 435, "NumTested": 77, "Math": 484, "M+CR+W": 1376, "M+CR": 941}, "960330": {"PerTested": 0.535, "CR": 467, "Writing": 453, "NumTested": 123, "Math": 500, "M+CR+W": 1420, "M+CR": 967}, "270306": {"PerTested": 0.624, "CR": 494, "Writing": 466, "NumTested": 153, "Math": 511, "M+CR+W": 1471, "M+CR": 1005}, "20302": {"PerTested": 0.408, "CR": 467, "Writing": 444, "NumTested": 142, "Math": 488, "M+CR+W": 1399, "M+CR": 955}, "821308": {"PerTested": 0.528, "CR": 463, "Writing": 456, "NumTested": 86, "Math": 477, "M+CR+W": 1396, "M+CR": 940}, "110416": {"PerTested": 0.752, "CR": 535, "Writing": 520, "NumTested": 245, "Math": 551, "M+CR+W": 1606, "M+CR": 1086}, "260408": {"PerTested": 0.539, "CR": 471, "Writing": 440, "NumTested": 173, "Math": 474, "M+CR+W": 1385, "M+CR": 945}, "790354": {"PerTested": 0.5660000000000001, "CR": 469, "Writing": 460, "NumTested": 112, "Math": 481, "M+CR+W": 1410, "M+CR": 950}, "410595": {"PerTested": 0.747, "CR": 494, "Writing": 485, "NumTested": 201, "Math": 500, "M+CR+W": 1479, "M+CR": 994}, "820820": {"PerTested": 0.491, "CR": 449, "Writing": 430, "NumTested": 241, "Math": 469, "M+CR+W": 1348, "M+CR": 918}, "940308": {"PerTested": 0.5, "CR": 420, "Writing": 408, "NumTested": 16, "Math": 438, "M+CR+W": 1266, "M+CR": 858}, "230230": {"PerTested": 0.586, "CR": 470, "Writing": 451, "NumTested": 589, "Math": 500, "M+CR+W": 1421, "M+CR": 970}, "580580": {"PerTested": 0.46799999999999997, "CR": 441, "Writing": 418, "NumTested": 101, "Math": 474, "M+CR+W": 1333, "M+CR": 915}, "920412": {"PerTested": 0.805, "CR": 574, "Writing": 556, "NumTested": 495, "Math": 580, "M+CR+W": 1710, "M+CR": 1154}, "790366": {"PerTested": 0.503, "CR": 442, "Writing": 423, "NumTested": 87, "Math": 464, "M+CR+W": 1329, "M+CR": 906}, "490335": {"PerTested": 0.895, "CR": 528, "Writing": 505, "NumTested": 374, "Math": 550, "M+CR+W": 1583, "M+CR": 1078}, "720720": {"PerTested": 0.54, "CR": 452, "Writing": 435, "NumTested": 68, "Math": 494, "M+CR+W": 1381, "M+CR": 946}, "320353": {"PerTested": 0.7829999999999999, "CR": 531, "Writing": 476, "NumTested": 36, "Math": 529, "M+CR+W": 1536, "M+CR": 1060}, "820388": {"PerTested": 0.551, "CR": 436, "Writing": 434, "NumTested": 59, "Math": 458, "M+CR+W": 1328, "M+CR": 894}, "320356": {"PerTested": 0.723, "CR": 450, "Writing": 426, "NumTested": 250, "Math": 464, "M+CR+W": 1340, "M+CR": 914}, "630630": {"PerTested": 0.584, "CR": 504, "Writing": 481, "NumTested": 468, "Math": 521, "M+CR+W": 1506, "M+CR": 1025}, "490346": {"PerTested": 0.45899999999999996, "CR": 494, "Writing": 473, "NumTested": 123, "Math": 527, "M+CR+W": 1494, "M+CR": 1021}, "140140": {"PerTested": 0.532, "CR": 477, "Writing": 459, "NumTested": 475, "Math": 505, "M+CR+W": 1441, "M+CR": 982}, "320365": {"PerTested": 0.731, "CR": 491, "Writing": 458, "NumTested": 291, "Math": 494, "M+CR+W": 1443, "M+CR": 985}, "320368": {"PerTested": 0.47600000000000003, "CR": 393, "Writing": 366, "NumTested": 111, "Math": 390, "M+CR+W": 1149, "M+CR": 783}, "670324": {"PerTested": 0.77, "CR": 485, "Writing": 457, "NumTested": 154, "Math": 501, "M+CR+W": 1443, "M+CR": 986}, "490354": {"PerTested": 0.563, "CR": 489, "Writing": 465, "NumTested": 120, "Math": 500, "M+CR+W": 1454, "M+CR": 989}, "410483": {"PerTested": 1.0, "CR": 405, "Writing": 371, "NumTested": 20, "Math": 394, "M+CR+W": 1170, "M+CR": 799}, "410484": {"PerTested": 0.662, "CR": 430, "Writing": 412, "NumTested": 143, "Math": 437, "M+CR+W": 1279, "M+CR": 867}, "360310": {"PerTested": 0.5820000000000001, "CR": 466, "Writing": 439, "NumTested": 156, "Math": 481, "M+CR+W": 1386, "M+CR": 947}, "410489": {"PerTested": 0.792, "CR": 519, "Writing": 502, "NumTested": 225, "Math": 528, "M+CR+W": 1549, "M+CR": 1047}, "410490": {"PerTested": 0.831, "CR": 545, "Writing": 532, "NumTested": 349, "Math": 561, "M+CR+W": 1638, "M+CR": 1106}, "920500": {"PerTested": 0.713, "CR": 511, "Writing": 497, "NumTested": 358, "Math": 529, "M+CR+W": 1537, "M+CR": 1040}, "540540": {"PerTested": 0.429, "CR": 444, "Writing": 420, "NumTested": 270, "Math": 468, "M+CR+W": 1332, "M+CR": 912}, "821821": {"PerTested": 0.528, "CR": 463, "Writing": 456, "NumTested": 86, "Math": 477, "M+CR+W": 1396, "M+CR": 940}, "850352": {"PerTested": 0.496, "CR": 472, "Writing": 453, "NumTested": 65, "Math": 499, "M+CR+W": 1424, "M+CR": 971}, "190336": {"PerTested": 0.593, "CR": 461, "Writing": 443, "NumTested": 89, "Math": 479, "M+CR+W": 1383, "M+CR": 940}, "670344": {"PerTested": 0.624, "CR": 458, "Writing": 433, "NumTested": 88, "Math": 471, "M+CR+W": 1362, "M+CR": 929}, "9090": {"PerTested": 0.479, "CR": 411, "Writing": 399, "NumTested": 146, "Math": 454, "M+CR+W": 1264, "M+CR": 865}, "970390": {"PerTested": 0.648, "CR": 495, "Writing": 469, "NumTested": 116, "Math": 519, "M+CR+W": 1483, "M+CR": 1014}, "190342": {"PerTested": 0.7759999999999999, "CR": 505, "Writing": 490, "NumTested": 128, "Math": 511, "M+CR+W": 1506, "M+CR": 1016}, "920455": {"PerTested": 0.7909999999999999, "CR": 514, "Writing": 493, "NumTested": 322, "Math": 531, "M+CR+W": 1538, "M+CR": 1045}, "780780": {"PerTested": 0.379, "CR": 419, "Writing": 405, "NumTested": 536, "Math": 450, "M+CR+W": 1274, "M+CR": 869}, "490380": {"PerTested": 0.435, "CR": 466, "Writing": 446, "NumTested": 87, "Math": 506, "M+CR+W": 1418, "M+CR": 972}, "60302": {"PerTested": 0.523, "CR": 509, "Writing": 468, "NumTested": 79, "Math": 502, "M+CR+W": 1479, "M+CR": 1011}, "360336": {"PerTested": 0.5, "CR": 441, "Writing": 428, "NumTested": 54, "Math": 462, "M+CR+W": 1331, "M+CR": 903}, "230361": {"PerTested": 0.86, "CR": 453, "Writing": 438, "NumTested": 178, "Math": 474, "M+CR+W": 1365, "M+CR": 927}, "920473": {"PerTested": 0.8270000000000001, "CR": 536, "Writing": 521, "NumTested": 463, "Math": 562, "M+CR+W": 1619, "M+CR": 1098}, "700317": {"PerTested": 0.66, "CR": 458, "Writing": 434, "NumTested": 142, "Math": 463, "M+CR+W": 1355, "M+CR": 921}, "7070": {"PerTested": 0.5429999999999999, "CR": 457, "Writing": 427, "NumTested": 215, "Math": 485, "M+CR+W": 1369, "M+CR": 942}, "530335": {"PerTested": 0.39799999999999996, "CR": 505, "Writing": 475, "NumTested": 33, "Math": 507, "M+CR+W": 1487, "M+CR": 1012}, "530336": {"PerTested": 0.594, "CR": 480, "Writing": 451, "NumTested": 148, "Math": 501, "M+CR+W": 1432, "M+CR": 981}, "410529": {"PerTested": 0.7879999999999999, "CR": 492, "Writing": 469, "NumTested": 230, "Math": 510, "M+CR+W": 1471, "M+CR": 1002}, "850850": {"PerTested": 0.485, "CR": 477, "Writing": 453, "NumTested": 213, "Math": 499, "M+CR+W": 1429, "M+CR": 976}, "995995": {"PerTested": 0.511, "CR": 504, "Writing": 483, "NumTested": 72, "Math": 538, "M+CR+W": 1525, "M+CR": 1042}, "600698": {"PerTested": 0.507, "CR": 416, "Writing": 398, "NumTested": 38, "Math": 439, "M+CR+W": 1253, "M+CR": 855}, "182182": {"PerTested": 0.623, "CR": 477, "Writing": 459, "NumTested": 129, "Math": 502, "M+CR+W": 1438, "M+CR": 979}, "530343": {"PerTested": 0.614, "CR": 465, "Writing": 437, "NumTested": 132, "Math": 490, "M+CR+W": 1392, "M+CR": 955}, "230312": {"PerTested": 0.647, "CR": 462, "Writing": 444, "NumTested": 145, "Math": 492, "M+CR+W": 1398, "M+CR": 954}, "860316": {"PerTested": 0.519, "CR": 495, "Writing": 469, "NumTested": 68, "Math": 530, "M+CR+W": 1494, "M+CR": 1025}, "870314": {"PerTested": 0.414, "CR": 487, "Writing": 461, "NumTested": 46, "Math": 473, "M+CR+W": 1421, "M+CR": 960}, "6060": {"PerTested": 0.523, "CR": 509, "Writing": 468, "NumTested": 79, "Math": 502, "M+CR+W": 1479, "M+CR": 1011}, "880880": {"PerTested": 0.618, "CR": 502, "Writing": 469, "NumTested": 141, "Math": 516, "M+CR+W": 1487, "M+CR": 1018}, "920495": {"PerTested": 0.7859999999999999, "CR": 520, "Writing": 501, "NumTested": 275, "Math": 536, "M+CR+W": 1557, "M+CR": 1056}, "410544": {"PerTested": 0.565, "CR": 398, "Writing": 378, "NumTested": 144, "Math": 409, "M+CR+W": 1185, "M+CR": 807}, "410545": {"PerTested": 0.9670000000000001, "CR": 440, "Writing": 413, "NumTested": 59, "Math": 452, "M+CR+W": 1305, "M+CR": 892}, "410547": {"PerTested": 0.736, "CR": 474, "Writing": 456, "NumTested": 206, "Math": 478, "M+CR+W": 1408, "M+CR": 952}, "230324": {"PerTested": 0.509, "CR": 476, "Writing": 456, "NumTested": 139, "Math": 508, "M+CR+W": 1440, "M+CR": 984}, "760760": {"PerTested": 0.499, "CR": 478, "Writing": 459, "NumTested": 548, "Math": 504, "M+CR+W": 1441, "M+CR": 982}, "5050": {"PerTested": 0.56, "CR": 483, "Writing": 466, "NumTested": 116, "Math": 522, "M+CR+W": 1471, "M+CR": 1005}, "400315": {"PerTested": 0.326, "CR": 449, "Writing": 428, "NumTested": 14, "Math": 426, "M+CR+W": 1303, "M+CR": 875}, "410556": {"PerTested": 0.584, "CR": 448, "Writing": 432, "NumTested": 129, "Math": 463, "M+CR+W": 1343, "M+CR": 911}, "181181": {"PerTested": 0.7120000000000001, "CR": 514, "Writing": 501, "NumTested": 156, "Math": 536, "M+CR+W": 1551, "M+CR": 1050}, "270270": {"PerTested": 0.624, "CR": 494, "Writing": 466, "NumTested": 153, "Math": 511, "M+CR+W": 1471, "M+CR": 1005}, "930700": {"PerTested": 0.983, "CR": 439, "Writing": 424, "NumTested": 57, "Math": 437, "M+CR+W": 1300, "M+CR": 876}, "410562": {"PerTested": 0.6970000000000001, "CR": 480, "Writing": 468, "NumTested": 214, "Math": 494, "M+CR+W": 1442, "M+CR": 974}, "360390": {"PerTested": 0.523, "CR": 474, "Writing": 457, "NumTested": 150, "Math": 500, "M+CR+W": 1431, "M+CR": 974}, "4040": {"PerTested": 0.537, "CR": 427, "Writing": 407, "NumTested": 159, "Math": 436, "M+CR+W": 1270, "M+CR": 863}, "800376": {"PerTested": 0.5, "CR": 448, "Writing": 442, "NumTested": 59, "Math": 480, "M+CR+W": 1370, "M+CR": 928}, "830348": {"PerTested": 0.545, "CR": 468, "Writing": 449, "NumTested": 12, "Math": 489, "M+CR+W": 1406, "M+CR": 957}, "360396": {"PerTested": 0.763, "CR": 485, "Writing": 460, "NumTested": 219, "Math": 503, "M+CR+W": 1448, "M+CR": 988}, "570318": {"PerTested": 0.395, "CR": 498, "Writing": 461, "NumTested": 58, "Math": 510, "M+CR+W": 1469, "M+CR": 1008}, "920528": {"PerTested": 0.08800000000000001, "CR": 332, "Writing": 314, "NumTested": 5, "Math": 362, "M+CR+W": 1008, "M+CR": 694}, "100307": {"PerTested": 0.544, "CR": 506, "Writing": 500, "NumTested": 43, "Math": 522, "M+CR+W": 1528, "M+CR": 1028}, "180180": {"PerTested": 0.565, "CR": 490, "Writing": 461, "NumTested": 651, "Math": 518, "M+CR+W": 1469, "M+CR": 1008}, "740309": {"PerTested": 0.444, "CR": 444, "Writing": 415, "NumTested": 48, "Math": 451, "M+CR+W": 1310, "M+CR": 895}, "3030": {"PerTested": 0.511, "CR": 481, "Writing": 450, "NumTested": 48, "Math": 490, "M+CR+W": 1421, "M+CR": 971}, "440440": {"PerTested": 0.442, "CR": 511, "Writing": 494, "NumTested": 236, "Math": 535, "M+CR+W": 1540, "M+CR": 1046}, "960335": {"PerTested": 0.414, "CR": 383, "Writing": 367, "NumTested": 58, "Math": 397, "M+CR+W": 1147, "M+CR": 780}, "590330": {"PerTested": 0.414, "CR": 475, "Writing": 460, "NumTested": 145, "Math": 497, "M+CR+W": 1432, "M+CR": 972}, "760380": {"PerTested": 0.517, "CR": 461, "Writing": 459, "NumTested": 78, "Math": 501, "M+CR+W": 1421, "M+CR": 962}, "490320": {"PerTested": 0.54, "CR": 523, "Writing": 513, "NumTested": 34, "Math": 491, "M+CR+W": 1527, "M+CR": 1014}, "360418": {"PerTested": 0.9470000000000001, "CR": 526, "Writing": 484, "NumTested": 125, "Math": 536, "M+CR+W": 1546, "M+CR": 1062}, "491491": {"PerTested": 0.706, "CR": 483, "Writing": 468, "NumTested": 278, "Math": 506, "M+CR+W": 1457, "M+CR": 989}, "2020": {"PerTested": 0.408, "CR": 467, "Writing": 444, "NumTested": 142, "Math": 488, "M+CR+W": 1399, "M+CR": 955}, "100326": {"PerTested": 0.483, "CR": 441, "Writing": 423, "NumTested": 85, "Math": 453, "M+CR+W": 1317, "M+CR": 894}, "960372": {"PerTested": 0.42, "CR": 486, "Writing": 454, "NumTested": 47, "Math": 489, "M+CR+W": 1429, "M+CR": 975}, "340568": {"PerTested": 0.867, "CR": 414, "Writing": 402, "NumTested": 26, "Math": 424, "M+CR+W": 1240, "M+CR": 838}, "960490": {"PerTested": 0.69, "CR": 536, "Writing": 514, "NumTested": 40, "Math": 556, "M+CR+W": 1606, "M+CR": 1092}, "360428": {"PerTested": 0.425, "CR": 459, "Writing": 425, "NumTested": 91, "Math": 453, "M+CR+W": 1337, "M+CR": 912}, "740333": {"PerTested": 0.706, "CR": 499, "Writing": 470, "NumTested": 187, "Math": 525, "M+CR+W": 1494, "M+CR": 1024}, "100334": {"PerTested": 0.415, "CR": 487, "Writing": 469, "NumTested": 103, "Math": 493, "M+CR+W": 1449, "M+CR": 980}, "1010": {"PerTested": 0.616, "CR": 467, "Writing": 452, "NumTested": 779, "Math": 499, "M+CR+W": 1418, "M+CR": 966}, "600496": {"PerTested": 0.7509999999999999, "CR": 456, "Writing": 440, "NumTested": 208, "Math": 461, "M+CR+W": 1357, "M+CR": 917}, "980980": {"PerTested": 0.542, "CR": 468, "Writing": 449, "NumTested": 396, "Math": 493, "M+CR+W": 1410, "M+CR": 961}, "760318": {"PerTested": 0.493, "CR": 451, "Writing": 432, "NumTested": 73, "Math": 485, "M+CR+W": 1368, "M+CR": 936}, "840361": {"PerTested": 0.848, "CR": 471, "Writing": 450, "NumTested": 39, "Math": 494, "M+CR+W": 1415, "M+CR": 965}, "740344": {"PerTested": 0.503, "CR": 463, "Writing": 437, "NumTested": 83, "Math": 492, "M+CR+W": 1392, "M+CR": 955}, "920436": {"PerTested": 0.6559999999999999, "CR": 473, "Writing": 447, "NumTested": 301, "Math": 499, "M+CR+W": 1419, "M+CR": 972}, "490490": {"PerTested": 0.604, "CR": 502, "Writing": 480, "NumTested": 847, "Math": 524, "M+CR+W": 1506, "M+CR": 1026}, "491312": {"PerTested": 0.706, "CR": 483, "Writing": 468, "NumTested": 278, "Math": 506, "M+CR+W": 1457, "M+CR": 989}, "100348": {"PerTested": 0.344, "CR": 479, "Writing": 465, "NumTested": 94, "Math": 504, "M+CR+W": 1448, "M+CR": 983}, "920368": {"PerTested": 0.677, "CR": 535, "Writing": 499, "NumTested": 289, "Math": 554, "M+CR+W": 1588, "M+CR": 1089}}